Workbook

Sheet nháp
A1: STT | B1: Tên trường đối tác | C1: Tên môn tại trường đối tác | D1: Mã môn tại trường đối tác | F1: Tên môn tại FTU | G1: Mã môn tại FTU | H1: Tình trạng
A2: 1 | B2: Hitotsubashi University | C2: 社会科学入門（経済学） | D2: 1DB10501 | F2: Tiếng Nhật Kinh tế | G2: TNHH303 | H2: Tương đương
A3: 2 | B3: Hitotsubashi University | C3: マーケティング・マネジメント | D3: 1BB20801 | F3: Tiếng Nhật Marketing quốc tế | G3: TNHH402 | H3: Tương đương
A4: 3 | B4: Hitotsubashi University | C4: 金融入門 | D4: 1BA12401 | F4: Tiếng Nhật Tài chính | G4: TNHH308 | H4: Tương đương
A5: 4 | B5: Hitotsubashi University | C5: 経営組織 | D5: 2BG50501 | F5: Tiếng Nhật Quản trị | G5: TNHH304 | H5: Tương đương
B6: Hitotsubashi University | C6: 経営組織 | D6: 2BF50501 | F6: Tiếng Nhật Quản trị | G6: TNHH304
A7: 5 | B7: Hitotsubashi University | C7: 経営哲学 | D7: 2BF50801 | F7: Tiếng Nhật Quản trị | G7: TNHH304 | H7: Tương đương
A8: 6 | B8: Hitotsubashi University | C8: 経営組織 | D8: 2BG50501 | E8: =H8& "với học phần "&F8 -> Không tương đương với học phần Tiếng Nhật kinh doanh quốc tế | F8: Tiếng Nhật kinh doanh quốc tế | G8: TNHH307 | H8: Không tương đương
B9: Hitotsubashi University | C9: 経営組織 | D9: 2BF50501 | E9: =H9& "với học phần "&F9 -> Không tương đương với học phần Tiếng Nhật kinh doanh quốc tế | F9: Tiếng Nhật kinh doanh quốc tế | G9: TNHH307 | H9: Không tương đương
A10: 7 | B10: Hitotsubashi University | C10: 経営者講義A | D10: 1BA12101 | E10: =H10& "với học phần "&F10 -> Không tương đương với học phần Tiếng Nhật kinh doanh quốc tế | F10: Tiếng Nhật kinh doanh quốc tế | G10: TNHH307 | H10: Không tương đương
A11: 8 | B11: Hitotsubashi University | C11: 特別講義（企業経営分析） | D11: 1BF45101 | E11: =H11& "với học phần "&F11 -> Không tương đương với học phần Tiếng Nhật kinh doanh quốc tế | F11: Tiếng Nhật kinh doanh quốc tế | G11: TNHH307 | H11: Không tương đương
A12: 9 | B12: Hitotsubashi University | C12: 企業金融の理論と実務（みずほ証券寄附講義） | D12: 1BB35501 | E12: =H12& "với học phần "&F12 -> Không tương đương với học phần Tiếng Nhật Tài chính | F12: Tiếng Nhật Tài chính | G12: TNHH308 | H12: Không tương đương
A13: 10 | B13: Hitotsubashi University | C13: マネジメント・コントロール | D13: 2BG50601 | E13: =H13& "với học phần "&F13 -> Không tương đương với học phần Tiếng Nhật Quản trị học | F13: Tiếng Nhật Quản trị học | G13: TNHH304 | H13: Không tương đương
A14: 11 | B14: Hitotsubashi University | C14: 経済学入門 | D14: 1EA10103 | E14: =H14& "với học phần "&F14 -> Không tương đương với học phần Tiếng Nhật Kinh tế | F14: Tiếng Nhật Kinh tế | G14: TNHH303 | H14: Không tương đương
A15: 12 | B15: Waseda University | C15: グローバルビジネス論 ２ | D15: MANX241L | F15: Tiếng Nhật kinh doanh quốc tế | G15: TNHH307 | H15: Tương đương
A16: 13 | B16: Waseda University | C16: 経営戦略 | D16: MANX231L | F16: Tiếng Nhật quản trị học | G16: TNHH304 | H16: Tương đương
A17: 14 | B17: Waseda University | C17: 経営学 | D17: MANX101L | F17: Tiếng Nhật quản trị học | G17: TNHH304 | H17: Tương đương
A18: 15 | B18: Waseda University | C18: マーケティング論 | D18: CMMM101L | F18: Tiếng Nhật Marketing quốc tế | G18: TNHH402 | H18: Tương đương
A19: 16 | B19: Waseda University | C19: マーケティング戦略論 | D19: CMMM401L | F19: Tiếng Nhật Marketing quốc tế | G19: TNHH402 | H19: Tương đương
A20: 17 | B20: Waseda University | C20: 国際商務論 | D20: CMMI331L | F20: Tiếng Nhật giao dịch thương mại quốc tế | G20: TNHH403 | H20: Tương đương
A21: 18 | B21: Waseda University | C21: 貿易契約論 | D21: CMMI431L | E21: =H21& "với học phần "&F21 -> Không tương đươngvới học phần Tiếng Nhật giao dịch thương mại quốc tế | F21: Tiếng Nhật giao dịch thương mại quốc tế | G21: TNHH403 | H21: Không tương đương
A22: 19 | B22: Waseda University | C22: 国際貿易理論 | D22: CMMI451L | E22: =H22& "với học phần "&F22 -> Không tương đươngvới học phần Tiếng Nhật giao dịch thương mại quốc tế | F22: Tiếng Nhật giao dịch thương mại quốc tế | G22: TNHH403 | H22: Không tương đương
A23: 20 | B23: Waseda University | C23: ミクロ経済学 | D23: ECNE201L | F23: Tiếng Nhật kinh tế | G23: TNHH303 | H23: Tương đương
A24: 21 | B24: Waseda University | C24: マクロ経済学 | D24: ECNE201L | F24: Tiếng Nhật kinh tế | G24: TNHH303 | H24: Tương đương
A25: 22 | B25: Waseda University | C25: 基礎経済学 | D25: ECNE101L | F25: Tiếng Nhật kinh tế | G25: TNHH303 | H25: Tương đương
A26: 23 | B26: Waseda University | C26: 金融入門 | D26: ECNA121L | F26: Tiếng Nhật Tài chính quốc tế | G26: TNHH308 | H26: Tương đương
A27: 24 | B27: Waseda University | C27: 金融論 | D27: ECNA221L | E27: =H27& "với học phần "&F27 -> Không tương đươngvới học phần Tiếng Nhật Tài chính quốc tế | F27: Tiếng Nhật Tài chính quốc tế | G27: TNHH308 | H27: Không tương đương

Sheet Tổng
A1: _ | B1: Nước | C1: Trường đối tác | D1: Tên môn tại trường đối tác | E1: Mã môn tại trường đối tác | F1: Tên môn tại FTU | G1: Mã môn tại FTU | H1: Chương trình | I1: Khoa/Viện | J1: Trưởng bộ môn xác nhận | K1: Thời gian ký nhận
A2: Asia | B2: China | C2: Shanghai University of Finance and Economics | D2: Anglo-American Contract Law | E2: 101808 | F2: Đang xét tương đương với học phần Pháp Luật Thương mại quốc tế | G2: PLU422, PLUE422, PLU422E | H2: Tiêu chuẩn, CLC, CTTT | I2: Luật
A3: Asia | B3: China | C3: Shanghai University of Finance and Economics | D3: Big Data Methods and Applications | E3: 0304 | F3: Lập trình cho phân tích dữ liệu và tính toán Khoa học (Programming for Data Analysis and Scientific Computing) | G3: TIN314, TINE314, TIN314E | H3: Tiêu chuẩn, CLC, CTTT | I3: Khoa CN&KHDL | J3: Nguyễn Văn Tăng | K3: 2026
A4: Asia | B4: China | C4: Shanghai University of Finance and Economics | D4: Corporate Finance | E4: 105512 | F4: Tài chính doanh nghiệp (Corporate Finance) | G4: TCHE321 | H4: CLC | I4: TCNH | J4: Nguyễn Việt Dũng | K4: 2026
A5: Asia | B5: China | C5: Shanghai University of Finance and Economics | D5: Corporate Finance | E5: 105512 | F5: Tài chính doanh nghiệp (Corporate Finance) | G5: TCH321E | H5: CTTT | I5: TCNH | J5: Nguyễn Việt Dũng
A6: Asia | B6: China | C6: Shanghai University of Finance and Economics | D6: Development Economics | E6: 5106 | F6: Không tương đương với học phần Kinh tế phát triển (Development Economics) | G6: KTEE406 | H6: CTTT | I6: KTQT | J6: Lý Hoàng Phú | K6: 2026
A7: Asia | B7: China | C7: Shanghai University of Finance and Economics | D7: Econometrics | E7: 108402 | F7: Kinh tế lượng (Econometrics) | G7: KTE309, KTEE309, KTE309E | H7: Tiêu chuẩn, CLC, CTTT | I7: KTQT | J7: Đinh Thị Thanh Bình | K7: 2026
A8: Asia | B8: China | C8: Shanghai University of Finance and Economics | D8: Financial Accounting | E8: 101314 | F8: Nguyên lý kế toán (Principles of Accounting) | G8: KET201, KETE201, KET201E | H8: Tiêu chuẩn, CLC, CTTT | I8: KTKT | J8: Trần Thị Kim Anh | K8: 2026
A9: Asia | B9: China | C9: Shanghai University of Finance and Economics | D9: Financial Accounting | E9: 101314 | F9: Kế toán tài chính (Financial Accounting) | G9: KETE301 | H9: Tiêu chuẩn, CLC, CTTT | I9: KTKT | J9: Trần Thị Kim Anh | K9: 2026
A10: Asia | B10: China | C10: Shanghai University of Finance and Economics | D10: Financial Instruments and Risk Management | E10: 103097 | F10: Quản trị rủi ro tài chính (Financial Risk Management) | G10: TCH409. TCHE409, TCH409E | H10: Tiêu chuẩn, CLC, CTTT | I10: TCNH | J10: Nguyễn Việt Dũng | K10: 2026
A11: Asia | B11: China | C11: Shanghai University of Finance and Economics | D11: Game Theory and Information Economics | E11: 101561 | F11: Không tương đương với học phần Tổ chức ngành (Industrial Organization) | G11: KTE408, KTEE408, KTE408E | H11: Tiêu chuẩn, CLC, CTTT | I11: KTQT | J11: Từ Thúy Anh | K11: 2026
A12: Asia | B12: China | C12: Shanghai University of Finance and Economics | D12: Game Theory and Information Economics | E12: 1414 | F12: Không tương đương với học phần Tổ chức ngành (Industrial Organization) | G12: KTE408, KTEE408, KTE408E | H12: Tiêu chuẩn, CLC, CTTT | I12: KTQT | J12: Từ Thúy Anh | K12: 2026
A13: Asia | B13: China | C13: Shanghai University of Finance and Economics | D13: Intermediate Macroeconomics | E13: 101562 | F13: Kinh tế vĩ mô 2 (Intermediate Macroeconomics) | G13: KTE402, KTEE402, KTE402E | H13: Tiêu chuẩn, CLC, CTTT | I13: KTQT | J13: Đinh Thị Thanh Bình | K13: 2026
A14: Asia | B14: China | C14: Shanghai University of Finance and Economics | D14: Intermediate Macroeconomics | E14: 1353 | F14: Kinh tế vĩ mô 2 (Intermediate Macroeconomics) | G14: KTEE402 | H14: CLC | I14: KTQT | J14: Đinh Thị Thanh Bình | K14: 2026
A15: Asia | B15: China | C15: Shanghai University of Finance and Economics | D15: International Finance: Theory and Practice | E15: 250246 | F15: Không tương đương với học phần Thanh toán quốc tế (International Payment) | G15: TCH412, TCHE412, TCH412E | H15: Tiêu chuẩn, CLC, CTTT | I15: TCNH | J15: Mai Thu Hiền | K15: 2024 | L15: =COUNTIF(J:J,"") -> 1229
A16: Asia | B16: China | C16: Shanghai University of Finance and Economics | D16: International Trade Law | E16: 311199 | F16: Không tương đương với học phần Giao dịch thương mại quốc tế (International Trade Transactions) | G16: TMA302, TMAE302, TMAH302, TMA302E | H16: Tiêu chuẩn, CLC, CTTT | I16: Viện KT&KDQT | J16: Phan Thị Thu Hiền | K16: 2024
A17: Asia | B17: China | C17: Shanghai University of Finance and Economics | D17: International Trade Law | E17: 311199 | F17: Không tương đương với học phần Chính sách thương mại quốc tế (International Trade Policy) | G17: TMA301, TMAH301, TMA301E | H17: Tiêu chuẩn, CLC, CTTT | I17: Viện KT&KDQT | J17: Vũ Thành Toàn | K17: 2024
A18: Asia | B18: China | C18: Shanghai University of Finance and Economics | D18: Optimization in Finance | E18: 106276 | F18: Đang xét tương đương với học phần Kinh tế học tài chính (Financial Economics) | G18: TCH341, TCHE341, TCH341E | H18: Tiêu chuẩn, CLC, CTTT | I18: TCNH
A19: Asia | B19: China | C19: Shanghai University of Finance and Economics | D19: Public Finance | E19: 102041 | F19: Tài chính công (Public Finance) | G19: TCH431 | H19: Tiêu chuẩn | I19: TCNH | J19: Nguyễn Thu Thủy | K19: 2026
A20: Asia | B20: China | C20: Shanghai University of Finance and Economics | D20: Public Policy | E20: 2147 | F20: Chính sách công (Public Policy) | G20: KTEE441 | H20: CLC | I20: KTQT | J20: Lý Hoàng Phú | K20: 2026
A21: Asia | B21: China | C21: Shanghai University of Finance and Economics | D21: Public Policy | E21: 100729 | F21: Chính sách công (Public Policy) | G21: KTE441, KTEE441, KTE441E | H21: Tiêu chuẩn, CLC, CTTT | I21: KTQT | J21: Lý Hoàng Phú | K21: 2026
A22: Asia | B22: China | C22: SouthWest University | D22: 《面向对象程序设计：C++》 | E22: 33320890 | F22: Lập trình hướng đối tượng (Object-Oriented Programming) | G22: COSH203 | H22: ĐHNNQT | I22: CN&KHDL
A23: Asia | B23: China | C23: SouthWest University | D23: 《计算与智能技术导论》 | E23: 21116644 | F23: Nhập môn AI và Khoa học dữ liệu (Introduction to AI and Data Science) | G23: COSH202 | H23: ĐHNNQT | I23: CN&KHDL
A24: Asia | B24: China | C24: SouthWest University | D24: 《计算机网路网络技术》 | E24: 33310870 | F24: Mạng máy tính (Computer Networks) | G24: COSH201 | H24: ĐHNNQT | I24: CN&KHDL
A25: Asia | B25: China | C25: Beijing Foreign Studies University | D25: Application of Information Tech | F25: Không tương đương với học phần Lập trình cho phân tích dữ liệu và tính toán khoa học (Programming for Data Analysis and Scientific Computing) | G25: TIN314E, TINH314 | H25: Tiêu chuẩn, CLC | I25: KHDL | J25: Nguyễn Văn Tăng | K25: 2025
A26: Asia | B26: China | C26: Beijing Foreign Studies University | D26: Introduction to Corporate finance | E26: LXS011 | F26: Tài chính doanh nghiệp (Corporate Finance) | G26: TCH321, TCHE321, TCH321E | H26: Tiêu chuẩn, CLC, CTTT | I26: TCNH | J26: Nguyễn Việt Dũng | K26: 2025
A27: Asia | B27: China | C27: Beijing Foreign Studies University | D27: Big Data Analysis | E27: BSZXS11 | F27: Đang xét tương đương với học phần Lập trình cho phân tích dữ liệu và tính toán Khoa học (Programming for Data Analysis and Scientific Computing) | G27: TIN314E, TINH314, TINE314, TIN314E | H27: Tiêu chuẩn, CLC, CTTT | I27: CN&KHDL
A28: Asia | B28: China | C28: Beijing Foreign Studies University | D28: Business communication | E28: LXS029 | F28: Không tương đương với học phần Truyền thông trong kinh doanh quốc tế (International Business Communication) | G28: MKT408, MKTE408, MKT408E | H28: Tiêu chuẩn, CLC, CTTT | I28: Viện KT&KDQT | J28: Nguyễn Thanh Bình | K28: 2025
A29: Asia | B29: China | C29: Beijing Foreign Studies University | D29: Business communication | F29: Không tương đương với học phần Văn hóa trong kinh doanh (Culture in Business) | G29: KTE325, KTEE325, KTE325E | H29: Tiêu chuẩn, CLC, CTTT | I29: Viện KT&KDQT | J29: Trần Thị Thu Hiền | K29: 2025
A30: Asia | B30: China | C30: Beijing Foreign Studies University | D30: Business Ethics | F30: Đạo đức kinh doanh (Business Ethics) | G30: QTR305, QTRE305, QTR305E | H30: Tiêu chuẩn, CLC, CTTT | I30: QTKD | J30: Ngô Quý Nhâm | K30: 2025
A31: Asia | B31: China | C31: Beijing Foreign Studies University | D31: Business Law | F31: Pháp luật kinh doanh quốc tế (International Business Law) | G31: PLU410, PLUE410, PLU410E | H31: Tiêu chuẩn, CLC, CTTT | I31: Luật | J31: Nguyễn Minh Hằng | K31: 2025
A32: Asia | B32: China | C32: Beijing Foreign Studies University | D32: Brand Management | F32: Thương hiệu trong kinh doanh quốc tế (Brand in International Business) | G32: MKT407, MTKE407, MKT407E | H32: Tiêu chuẩn, CLC, CTTT | I32: Viện KT&KDQT | J32: Vũ Thành Toàn | K32: 2025
A33: Asia | B33: China | C33: Beijing Foreign Studies University | D33: Cross Cultural Management | F33: Văn hóa trong kinh doanh (Culture in Business) | G33: KTE325, KTEE325, KTE325E | H33: Tiêu chuẩn, CLC, CTTT | I33: Viện KT&KDQT | J33: Phan Thị Thu Hiền | K33: 2025
A34: Asia | B34: China | C34: Beijing Foreign Studies University | D34: Cross Cultural Management | F34: Quản trị đa văn hóa | G34: QTR408, QTRE408, QTR408E | H34: Tiêu chuẩn, CLC, CTTT | I34: QTKD | J34: Ngô Quý Nhâm | K34: 2026
A35: Asia | B35: China | C35: Beijing Foreign Studies University | D35: Data Analytics | F35: Không tương đương với học phần Phân tích dữ liệu trong kinh doanh (Business Analytics) | G35: VJP205, VJPE205, VJP205E | H35: Tiêu chuẩn, CLC., CTTT | I35: VJCC | J35: Hoàng Anh Duy | K35: 2025
A36: Asia | B36: China | C36: Beijing Foreign Studies University | D36: E-Commerce in China | F36: Thương mại điện tử | G36: TMA306, TMAE306, TMA306E | H36: Tiêu chuẩn, CLC, CTTT | I36: Viện KT&KDQT | J36: Nguyễn Hồng Quân | K36: 2026
A37: Asia | B37: China | C37: Beijing Foreign Studies University | D37: Human Resource Management | F37: Quản trị nguồn nhân lực | G37: QTR403, QTRE403, QTR403E | H37: Tiêu chuẩn, CLC, CTTT | I37: QTKD | J37: Ngô Quý Nhâm | K37: 2026
A38: Asia | B38: China | C38: Beijing Foreign Studies University | D38: International Finance | F38: Không tương đương với học phần Tài chính quốc tế (International Finance) | G38: TCH414, TCHE414, TCH414E | H38: Tiêu chuẩn, CLC, CTTT | I38: TCNH | J38: Mai Thu Hiền | K38: 2025
A39: Asia | B39: China | C39: Beijing Foreign Studies University | D39: International Trade | F39: Chính sách thương mại quốc tế (International Trade Policy) | G39: TMA301, TMAE301, TMA301E | H39: Tiêu chuẩn, CLC, CTTT | I39: Viện KT&KDQT | J39: Vũ Thành Toàn | K39: 2025
A40: Asia | B40: China | C40: Beijing Foreign Studies University | D40: Introduction to Business | F40: Nhập môn kinh doanh (Introduction to Business) | G40: KDO203, KDOE203, KDO203E | H40: Tiêu chuẩn, CLC, CTTT | I40: Viện KT&KDQT | J40: Trần Thị Thu Hiền | K40: 2025
... A47: Asia | B47: China | C47: Beijing Foreign Studies University | D47: Project Management | F47: Quản trị dự án | G47: QTR407, QTRE407, QTR407E | H47: Tiêu chuẩn, CLC, CTTT | I47: QTKD | J47: Nguyễn Thúy Anh | K47: 2026
A48: Asia | B48: China | C48: Beijing International Studies University | D48: Big Data Analysis | E48: BSZXS10 | F48: Không tương đương với học phần Phân tích dữ liệu kinh doanh | G48: VJP205, VJPE205, VJP205E | H48: Tiêu chuẩn, CLC, CTTT | I48: VJCC | J48: Hoàng Anh Duy | K48: 2026
A49: Asia | B49: China | C49: Beijing International Studies University | D49: Big Data Analysis | E49: BSZXS10 | F49: Lập trình cho phân tích dữ liệu và tính toán Khoa học (Programming for Data Analysis and Scientific Computing) | G49: TIN314, TINE314/ TINH314, TIN314E | H49: Tiêu chuẩn, CLC, CTTT | I49: CN&KHDL | J49: Nguyễn Văn Tăng | K49: 2026
A50: Asia | B50: China | C50: Beijing International Studies University | D50: Developing an International Business Strategy | E50: BSZXS04 | F50: Thương hiệu trong kinh doanh quốc tế | G50: MKT407, MTKE407, MKT407E | H50: Tiêu chuẩn, CLC, CTTT | I50: Viện KT&KDQT | J50: Vũ Thành Toàn | K50: 2026
A51: Asia | B51: China | C51: Beijing International Studies University | D51: Brand Management | E51: BSZXS04 | F51: Không tương đương với học phần Marketing quốc tế (International Marketing) | G51: MKT401, MKTE401, MKT401E | H51: Tiêu chuẩn, CLC, CTTT | I51: Viện KT&KDQT | J51: Nguyễn Thanh Bình | K51: 2025
A52: Asia | B52: China | C52: Beijing International Studies University | D52: Business Law | F52: Pháp luật kinh doanh quốc tế (International Business Law) | G52: PLU410, PLUE410, PLU410E | H52: Tiêu chuẩn, CLC, CTTT | I52: Luật | J52: Nguyễn Minh Hằng | K52: 2025
A53: Asia | B53: China | C53: Beijing International Studies University | D53: Corporate Governance | F53: Không tương đương với học phần Tiếng Anh chuyên ngành 3 (Quản trị kinh doanh) | G53: ESP232 | H53: Tiêu chuẩn | I53: QTKD | J53: Hoàng Huệ Chi | K53: 2025
A54: Asia | B54: China | C54: Beijing International Studies University | D54: Consumer Behavior | E54: BSZX05 | F54: Không tương đương với học phần Quan hệ khách hàng trong kinh doanh (Business Customer Relationship) | G54: MKT402, MKTE402, MKT402E | H54: Tiêu chuẩn, CLC, CTTT | I54: Viện KT&KDQT | J54: Nguyễn Thanh Bình | K54: 2025
A55: Asia | B55: China | C55: Beijing International Studies University | D55: Corporate Transformation: Theory&Practice | E55: BSZXS12 | F55: Sáng tạo kinh doanh | G55: TMA327, TMAE327, TMA327E | H55: Tiêu chuẩn, CLC, CTTT | I55: Viện KT&KDQT | J55: Vũ Thành Toàn | K55: 2026
A56: Asia | B56: China | C56: Beijing International Studies University | D56: Digital Marketing | E56: BSZXS02 | F56: Không tương đương với học phần Marketing số (Digital Marketing) | G56: MKT206, MKTE206, MKT206E | H56: Tiêu chuẩn, CLC, CTTT | I56: Viện KT&KDQT | J56: Nguyễn Thanh Bình | K56: 2025
A57: Asia | B57: China | C57: Beijing International Studies University | D57: Digital Marketing | F57: Marketing số | G57: MKT206, MKTE206, MKT206E | H57: Tiêu chuẩn, CLC, CTTT | I57: Viện KT&KDQT | J57: Nguyễn Thanh Bình | K57: 2026
A58: Asia | B58: China | C58: Beijing International Studies University | D58: Digital Marketing | F58: Không tương đương với học phần Digital Marketing | G58: MKT406, MKTE406, MKT406E | H58: Tiêu chuẩn, CLC, CTTT | I58: Viện KT&KDQT | J58: Nguyễn Thanh Bình | K58: 2026
A59: Asia | B59: China | C59: Beijing International Studies University | D59: English Speech and Communication | F59: Tiếng anh chuyên ngành 5 (Diễn thuyết trước công chúng) | G59: ESP451 | H59: CLC | I59: TACN | J59: Hoàng Huệ Chi | K59: 2026
A60: Asia | B60: China | C60: Beijing International Studies University | D60: Financial Mangement | E60: BSZB010 | F60: Không tương đương với học phần Phân tích đầu tư chứng khoán | G60: DTU401, DTUE401, DTU401E | H60: Tiêu chuẩn, CLC, CTTT | I60: TCNH | J60: Nguyễn Việt Dũng | K60: 2026
A61: Asia | B61: China | C61: Beijing International Studies University | D61: Global Business Management | E61: BSZB017 | F61: Không tương đương với học phần Nghiệp vụ kinh doanh quốc tế | G61: KDO408, KDOE408, KDO408E | H61: Tiêu chuẩn, CLC, CTTT | I61: Viện KT&KDQT | J61: Phan Thị Thu Hiền | K61: 2026
A62: Asia | B62: China | C62: Beijing International Studies University | D62: Global Business Management | E62: BSZB017 | F62: Không tương đương với học phần Chuỗi giá trị toàn cầu | G62: KDO304, KDOE304, KDO304E | H62: Tiêu chuẩn, CLC, CTTT | I62: Viện KT&KDQT | J62: Phan Thị Thu Hiền | K62: 2026
A63: Asia | B63: China | C63: Beijing International Studies University | D63: International Marketing | E63: BSZXZ01 | F63: Không tương đương với học phần Marketing quốc tế (International Marketing) | G63: MKT401, MKTE401, MKT401E | H63: Tiêu chuẩn, CLC, CTTT | I63: Viện KT&KDQT | J63: Nguyễn Thanh Bình | K63: 2025
A64: Asia | B64: China | C64: Beijing International Studies University | D64: Intercuitural Communication and Management | F64: Không tương đương với học phần Quan hệ quốc tế (International Relations) | G64: TMA317, TMAE317, TMA317E | H64: Tiêu chuẩn, CLC, CTTT | I64: Viện KT&KDQT | J64: Vũ Thành Toàn | K64: 2025
A65: Asia | B65: China | C65: Beijing International Studies University | D65: International Business | F65: Đang xét tương đương với học phần Kinh doanh quốc tế (International Business) | G65: KDO307, KDOE307, KDO307E | H65: Tiêu chuẩn, CLC, CTTT | I65: Viện KT&KDQT
A66: Asia | B66: China | C66: Beijing International Studies University | D66: Introduction to Business | F66: Đang xét tương đương với học phần Nhập môn kinh doanh (Introduction to Business) | G66: KDO203, KDOE203, KDO203E | H66: Tiêu chuẩn, CLC, CTTT | I66: Viện KT&KDQT
A67: Asia | B67: China | C67: Beijing International Studies University | D67: International Contracts & Payments | F67: Đang xét tương đương với học phần Thanh toán quốc tế (International Payment) | G67: TCH412, TCHE412, TCH412E | H67: Tiêu chuẩn, CLC, CTTT | I67: TCNH
A68: Asia | B68: China | C68: Beijing International Studies University | D68: Managerial Communication | E68: BSZXS08 | F68: Không tương đương với học phần Đàm phán và Quản trị xung đột | G68: KDO302, KDOE302, KDO302E | H68: Tiêu chuẩn, CLC, CTTT | I68: Viện KT&KDQT | J68: Phan Thị Thu Hiền | K68: 2026
A69: Asia | B69: China | C69: Beijing International Studies University | D69: Risk Management | F69: Quản lý rủi ro trong kinh doanh quốc tế (Risk Management in International Business) | G69: KDO402, KDOE402, KDO402E | H69: Tiêu chuẩn, CLC, CTTT | I69: Viện KT&KDQT | J69: Trịnh Thị Thu Hương | K69: 2025
A70: Asia | B70: China | C70: Beijing International Studies University | D70: Operations Management | F70: Không tương đương với học phần Quản lý chuỗi cung ứng (Supply Chain Management) | G70: TMA313, TMAE313, TMA313E | H70: Tiêu chuẩn, CLC, CTTT | I70: Viện KT&KDQT | J70: Trịnh Thị Thu Hương | K70: 2024
A71: Asia | B71: China | C71: Beijing International Studies University | D71: Operations Management | F71: Quản lý sản xuất và vận hành (Operation and Production Management in Supply Chain) | G71: KTEE337 | H71: CLC | I71: Viện KT&KDQT | J71: Trịnh Thị Thu Hương | K71: 2026
A72: Asia | B72: China | C72: Beijing International Studies University | D72: International Financial Management | F72: Tài chính quốc tế (International Finance) | G72: TCH414, TCHE414, TCH414E | H72: Tiêu chuẩn, CLC, CTTT | I72: TCNH | J72: Mai Thu Hiền | K72: 2025
A73: Asia | B73: China | C73: Beijing International Studies University | D73: Quantative Investment Strategy | E73: BSZXS13 | F73: Phân tích đầu tư chứng khoán | G73: DTU402, DTUE401, DTU401E | H73: Tiêu chuẩn, CLC, CTTT | I73: TCNH | J73: Nguyễn Việt Dũng | K73: 2026
A74: Asia | B74: China | C74: Beijing International Studies University | D74: Service Marketing | E74: BSZXS11 | F74: Không tương đương với học phần Quan hệ khách hàng trong kinh doanh | G74: MKT402, MKTE402, MKT402E | H74: Tiêu chuẩn, CLC, CTTT | I74: Viện KT&KDQT | J74: Nguyễn Thanh Bình | K74: 2026
A75: Asia | B75: China | C75: Beijing International Studies University | D75: Strategic Management | E75: BSZB012 | F75: Không tương đương với học phần Quản lý dự án đầu tư quốc tế | G75: TMA315, TMAE315, TMA315E | H75: Tiêu chuẩn, CLC, CTTT | I75: Viện KT&KDQT
A76: Asia | B76: China | C76: Lingnan University | D76: Financial Management | E76: BUS2201 | F76: Đang xét tương đương với học phần Lý thuyết tài chính | G76: TCH302 | H76: Tiêu chuẩn | I76: TCNH
A77: Asia | B77: Japan | C77: Aichi University | D77: Japanese II B [Grammar/ Reading Comprehension] | F77: Ngữ pháp tiếng Nhật nâng cao | G77: TNH227 | H77: Tiêu chuẩn | I77: Tiếng Nhật | J77: Phạm Quang Hưng | K77: 2022
A78: Asia | B78: Japan | C78: Aichi University | D78: Japanese III B [Conversation/ Listening Comprehension] | F78: Không tương đương với học phần nào của bộ môn Thực hành tiếng | I78: Tiếng Nhật | J78: Đinh Thị Ngọc Quỳnh | K78: 2022
A79: Asia | B79: Japan | C79: Akita International University | D79: Accounting | E79: ECN310 | F79: Không tương đương với học phần Kế toán quốc tế (International Accounting) | G79: KET410, KETE410, KET410E | H79: Tiêu chuẩn, CLC, CTTT | I79: KTKT | J79: Trần Thị Kim Anh | K79: 2022
A80: Asia | B80: Japan | C80: Akita International University | D80: Analysis of Economic Data | E80: ECN220 | F80: Phân tích dữ liệu kinh doanh (Business Analysis) | G80: VJP205, VJPE205, VJP205E | H80: Tiêu chuẩn, CLC, CTTT | I80: VJCC | J80: Hoàng Anh Duy | K80: 2025
A81: Asia | B81: Japan | C81: Akita International University | D81: Artficial Intelligence & Humanity | E81: DGT330 | F81: Trí tuệ nhân tạo trong kỷ nguyên số (AI in the Era of Digital Transformation) | G81: AIDE300 | H81: CLC | I81: Khoa CN&KHDL | J81: Nguyễn Văn Tăng | K81: 2025
A82: Asia | B82: Japan | C82: Akita International University | D82: Economic Development | F82: Kinh tế phát triển (Development Economics) (Development Economics) | G82: KTE406, KTEE406 | H82: Tiêu chuẩn, CLC | I82: KTQT | J82: Từ Thuý Anh | K82: 2021
A83: Asia | B83: Japan | C83: Akita International University | D83: Money, Banking and Financial Markets | F83: Tiền tệ - Ngân hàng (Money and Banking) | G83: TCH303, TCHE303 | H83: Tiêu chuẩn, CLC | I83: TCNH | J83: Nguyễn Thu Thủy | K83: 2024
A84: Asia | B84: Japan | C84: Akita International University | D84: Health & Physical Education Activities I | E84: HPE110 | F84: Giáo dục thể chất 3 | G84: GDTC3 | H84: Tiêu chuẩn, CLC, CTTT | I84: GDTC | K84: 2025
A85: Asia | B85: Japan | C85: Akita International University | D85: International Business Law | E85: ECN309 | F85: Không tương đương với học phần Pháp luật kinh doanh quốc tế (International Business Law) | G85: PLU410, PLUE410. PLU410E | H85: Tiêu chuẩn, CLC, CTTT | I85: Luật | J85: Nguyễn Minh Hằng | K85: 2024
A86: Asia | B86: Japan | C86: Akita International University | D86: International Financial Management | E86: ECN230-1_F | F86: Đang xét tương đương với học phần Thị trường và quản trị tài chính | G86: TCH422F | H86: ĐHNNQT | I86: TCNH
A87: Asia | B87: Japan | C87: Akita International University | D87: International Relations | E87: PLS210 | F87: Quan hệ quốc tế (International Relations) | G87: TMA317, TMAE317, TMA317E | H87: Tiêu chuẩn, CLC, CTTT | I87: Viện KT&KDQT | J87: Vũ Thành Toàn | K87: 2025
A88: Asia | B88: Japan | C88: Akita International University | D88: Corporate Finance | E88: ECN330 | F88: Tài chính doanh nghiệp (Corporate Finance) | G88: TCH321, TCHE321, TCH321E | H88: Tiêu chuẩn, CLC, CTTT | I88: TCNH | J88: Nguyễn Việt Dũng | K88: 2025
A89: Asia | B89: Japan | C89: Akita International University | D89: Corporate Finance | E89: ECN330 | F89: Không tương đương với học phần Thị trường và quản trị tài chính | G89: TCH422F | H89: ĐHNNQT | I89: TCNH | J89: Nguyễn Việt Dũng | K89: 2026
A90: Asia | B90: Japan | C90: Akita International University | D90: Digital Marketing Strategy | E90: ECN391 | F90: Không tương đương với học phần Chiến lược và kế hoạch Marketing (Marketing Planning and Strategies) | G90: MKT308, MKTE308, MKT308E, MKTH308 | H90: Tiêu chuẩn, CLC, CTTT. ĐHNNQT | I90: Viện KT&KDQT | J90: Nguyễn Thanh Bình | K90: 2025
A91: Asia | B91: Japan | C91: Akita International University | D91: Eco-Business and Sustainability | E91: ECN344 | F91: Không tương đương với học phần Đạo đức kinh doanh và trách nhiệm xã hội của doanh nghiệp (Business Ethics and Corporate Social Responsibility) | G91: KDOH305 | H91: ĐHNNQT | I91: Viện KT&KDQT | J91: Phan Thị Thu Hiền | K91: 2025
A92: Asia | B92: Japan | C92: Akita International University | D92: Environmental Economics | E92: ECN368 | F92: Kinh tế môi trường (Environmental Economics) | G92: KTE404, KTEE404, KTE404E | H92: Tiêu chuẩn, CLC, CTTT | I92: Viện KT&KDQT | J92: Lý Hoàng Phú | K92: 2025
A93: Asia | B93: Japan | C93: Akita International University | D93: Entrepreneurial Thinking & Innovation | E93: ECN254 | F93: Đổi mới sáng tạo trong kinh doanh số (Innovation in Digital Business) | G93: MKT202, MKTE202, MKT202E | H93: Tiêu chuẩn, CLC, CTTT | I93: Viện KT&KDQT | J93: Vũ Thành Toàn | K93: 2025
A94: Asia | B94: Japan | C94: Akita International University | D94: Entrepreneurial Thinking & Innovation | E94: ECN254 | F94: Lập dự án kinh doanh số | G94: MKTH307 | H94: CLC | I94: Viện KT&KDQT | J94: Đỗ Ngọc Kiên
A95: Asia | B95: Japan | C95: Akita International University | D95: Global Marketing | E95: ECN318 | F95: Không tương đương với học phần Marketing quốc tế (International Marketing) | G95: MKTE401, MKT401, MKT401E | H95: Tiêu chuẩn, CLC, CTTT | I95: Viện KT&KDQT | J95: Nguyễn Thanh Bình | K95: 2025
A96: Asia | B96: Japan | C96: Akita International University | D96: Global Marketing | E96: ECN318 | F96: Quản trị marketing toàn cầu | G96: MKTE201 | H96: ĐHNNQT | I96: Viện KT&KDQT | J96: Nguyễn Thanh Bình | K96: 2026
A97: Asia | B97: Japan | C97: Akita International University | D97: International Cooperation and Development II | E97: SOC335 | F97: Không tương đương với học phần Quản trị dự án quốc tế | G97: TMA315, TMAE315, TMA315E | H97: Tiêu chuẩn, CLC, CTTT | I97: Viện KT&KDQT | J97: Đỗ Ngọc Kiên | K97: 2026
A98: Asia | B98: Japan | C98: Akita International University | D98: International Business | E98: ECN240 | F98: Kinh doanh quốc tế (International Business) | G98: KDO307, KDOE307, KDO307E | H98: Tiêu chuẩn, CLC, CTTT | I98: Viện KT&KDQT | J98: Phan Thị Thu Hiền | K98: 2026
A99: Asia | B99: Japan | C99: Akita International University | D99: Psychology 1: Human Universals in Psychology | E99: PSY151 | F99: Không tương đương với học phần Tâm lý học (Psychology) | G99: TLHH101 | H99: CLC | I99: Khoa KHCT&NV | J99: Nguyễn Mai Phương | K99: 2025
A100: Asia | B100: Japan | C100: Akita International University | D100: Speech Communication | E100: ENG102 | F100: Không tương đương với học phần Tiếng anh chuyên ngành 5 (Diễn thuyết trước công chúng) | G100: ESP451 | H100: CLC | I100: TACN | J100: Hoàng Huệ Chi | K100: 2025
A101: Asia | B101: Japan | C101: Doshisha Women's College of Liberal Arts (DWCLA) | D101: Intermediate Business Administration | E101: 441900 | F101: Ngôn ngữ kinh tế thương mại 8: Quản trị kinh doanh | G101: TNH412 | H101: Tiêu chuẩn | I101: Tiếng Nhật | J101: Nguyễn Thị Bích Huệ | K101: 2025
A102: Asia | B102: Japan | C102: Doshisha Women's College of Liberal Arts (DWCLA) | D102: Japanese Composition II A | E102: 245760 | F102: Không tương đương với học phần Viết II | G102: TNH310 | H102: Tiêu chuẩn | I102: Tiếng Nhật | J102: Phạm Quang Hưng | K102: 2023
A103: Asia | B103: Japan | C103: Doshisha Women's College of Liberal Arts (DWCLA) | D103: Japanese Grammar I | E103: 246860 | F103: Ngữ pháp tiếng Nhật nâng cao | G103: TNH227 | H103: Tiêu chuẩn | I103: Tiếng Nhật | J103: Phạm Quang Hưng | K103: 2023
A104: Asia | B104: Japan | C104: Doshisha Women's College of Liberal Arts (DWCLA) | D104: Japanese Reading Comprehension II A | E104: 245360 | F104: Không tương đương với học phần Đọc II | G104: TNH306 | H104: Tiêu chuẩn | I104: Tiếng Nhật | J104: Phạm Quang Hưng | K104: 2022
A105: Asia | B105: Japan | C105: Doshisha Women's College of Liberal Arts (DWCLA) | D105: Management Theory | E105: 415500 | F105: Ngôn ngữ kinh tế thương mại 8: Quản trị kinh doanh | G105: TNH412 | H105: Tiêu chuẩn | I105: Tiếng Nhật | J105: Nguyễn Thị Bích Huệ | K105: 2022
A106: Asia | B106: Japan | C106: Doshisha Women's College of Liberal Arts (DWCLA) | D106: 中約中国語 I | E106: 032101 | F106: Ngoại ngữ 2 - phần 1 (Tiếng Trung) | G106: TTR161 | H106: Tiêu chuẩn | I106: Tiếng Trung | J106: Nguyễn Thị Bích Ngọc | K106: 2022
...

Sheet Count trưởng bộ môn
A1: STT | B1: Trưởng bộ môn xác nhận | C1: Đếm môn
A2: 1 | B2: Nguyễn Thị Bích Huệ | C2: =countif('Tổng'!J:J,B2) -> 317
A3: 2 | B3: Nguyễn Việt Dũng | C3: =countif('Tổng'!J:J,B3) -> 260
A4: 3 | B4: Ngô Quý Nhâm | C4: =countif('Tổng'!J:J,B4) -> 312
A5: 4 | B5: Nguyễn Thanh Bình | C5: =countif('Tổng'!J:J,B5) -> 287
A6: 5 | B6: Phan Thị Thu Hiền | C6: =countif('Tổng'!J:J,B6) -> 241
A7: 6 | B7: Phạm Quang Hưng | C7: =countif('Tổng'!J:J,B7) -> 152
A8: 7 | B8: Vũ Thành Toàn | C8: =countif('Tổng'!J:J,B8) -> 272
A9: 8 | B9: Lê Thái Phong | C9: =countif('Tổng'!J:J,B9) -> 219
A10: 9 | B10: Mai Thu Hiền | C10: =countif('Tổng'!J:J,B10) -> 117
A11: 10 | B11: Từ Thuý Anh | C11: =countif('Tổng'!J:J,B11) -> 88
A12: 11 | B12: Trịnh Thị Thu Hương | C12: =countif('Tổng'!J:J,B12) -> 152
A13: 12 | B13: Trần Thị Kim Anh | C13: =countif('Tổng'!J:J,B13) -> 104
... A49: 48 | B49: Nguyễn Thị Thuỳ Vinh | C49: =countif('Tổng'!J:J,B49) -> 1

Sheet Stage 3 Outbound recheck
A2: Chưa có chữ ký của trưởng bộ môn | B2: Asia | C2: Japan | D2: Fukuyama University | E2: Giới thiệu về kinh tế học | G2: Không tương đương với học phần nào của bộ môn
A3: Chưa có chữ ký của trưởng bộ môn | B3: Asia | C3: Japan | D3: Fukuyama University | E3: Kinh tế Mỹ II | G3: Không tương đương với học phần nào của bộ môn
A4: Chưa có chữ ký của trưởng bộ môn | B4: Asia | C4: Japan | D4: Fukuyama University | E4: Seminar in English II | G4: Không tương đương với học phần nào của bộ môn
A5: Chưa có chữ ký của trưởng bộ môn | B5: Asia | C5: Japan | D5: Fukuyama University | E5: Tiếng Anh IV | G5: Không tương đương với học phần nào của bộ môn
A6: 25 | B6: Asia | C6: Japan | D6: Hiroshima University of Economics | E6: 交換留学日本語（上級AI | F6: 36027 | G6: Ngoại ngữ 4 | H6: TNH232 | I6: Tiêu chuẩn | J6: KTĐN
A7: 26 | B7: Asia | C7: Japan | D7: Hiroshima University of Economics | E7: 交換留学日本語（上級AI | F7: 36027 | G7: Ngoại ngữ 5 | H7: TNH331 | I7: Tiêu chuẩn | J7: KTĐN
A8: 27 | B8: Asia | C8: Japan | D8: Hiroshima University of Economics | E8: 交換留学日本語（上級BI | F8: 36029 | G8: Ngoại ngữ 4 | H8: TNH232 | I8: Tiêu chuẩn | J8: KTĐN
A9: 28 | B9: Asia | C9: Japan | D9: Hiroshima University of Economics | E9: 交換留学日本語（上級BI | F9: 36029 | G9: Ngoại ngữ 5 | H9: TNH331 | I9: Tiêu chuẩn | J9: KTĐN
A10: 44 | B10: Asia | C10: Japan | D10: Hitotsubashi University | E10: 日本語中上級(漢字語彙) | G10: Từ vựng tiếng Nhật nâng cao | H10: TNH226 | I10: Tiêu chuẩn | J10: Tiếng Nhật
B11: Asia | C11: Japan | D11: Hitotsubashi University | E11: Corporate Finance | G11: Không tương đương với học phần Tài chính Quốc tế
A12: 17 | B12: Asia | C12: Japan | D12: Hitotsubashi University | E12: ビジネス・コミュニケーション… | G12: Không tương đương với Nghe - đọc thương mại 1
A13: 18 | B13: Asia | C13: Japan | D13: Hitotsubashi University | E13: ビジネス・コミュニケーション… | G13: Không tương đương với Nghe - đọc thương mại 2
B14: Asia | C14: Japan | D14: Hitotsubashi University | E14: Special Topics on Management and Marketing E | F14: 1BB38501 | G14: Kỹ năng lãnh đạo và phát triển cá nhân | H14: QTRE203; QTR203; QTR203E
B15: Asia | C15: Japan | D15: Hitotsubashi University | E15: Interactive Course on Business Basics (Finance) | F15: 1BB27601 | G15: Khoa đề xuất tương đương với học phần Quản trị tài chính doanh nghiệp (KET307) tuy nhiên cần bổ sung giải thích credit của trường Hitotsubashi
A16: Chưa có chữ ký của trưởng bộ môn | B16: Asia | C16: Japan | D16: Hitotsubashi University | E16: 特別講義 (社会課題の解決) | F16: 1BB36101 | G16: Không tương đương với học phần Đạo đức kinh doanh và trách nhiệm xã hội | H16: KDOH305 | I16: CLC
A19: 58 | B19: Asia | C19: Japan | D19: J. F. Oberlin University | E19: 国際貿易論 | F19: 22384 | G19: Tiếng Nhật giao dịch thương mại quốc tế | H19: TNHH403 | I19: CLC | J19: Tiếng Nhật
A20: 57 | B20: Asia | C20: Japan | D20: J. F. Oberlin University | E20: 国際貿易論 | F20: 22384 | G20: Ngôn ngữ KTTM 3: Giao dịch thương mại | H20: TNH404 | I20: Tiêu chuẩn | J20: Tiếng Nhật
A21: 55 | B21: Asia | C21: Japan | D21: J. F. Oberlin University | E21: 日本の文化（Ｅ）（GS_RL） | F21: 285034 | G21: Văn hóa văn minh Nhật Bản | H21: TNH315 | I21: Tiêu chuẩn | J21: Tiếng Nhật
A22: 56 | B22: Asia | C22: Japan | D22: J. F. Oberlin University | E22: 日本の文化（Ｅ）（GS_RL） | F22: 285034 | G22: Xã hội Nhật Bản | H22: TNHH210 | I22: CLC | J22: Tiếng Nhật
A23: 59 | B23: Asia | C23: Japan | D23: J. F. Oberlin University | E23: 異文化経営論 | F23: 26184 | G23: Tiếng Nhật Kinh doanh QT | H23: TNHH307 | I23: CLC | J23: Tiếng Nhật
B24: Asia | C24: Japan | D24: J. F. Oberlin University | E24: キャリアデザインD (留学生用) | F24: 201461 | G24: Định hướng nghề nghiệp | H24: TNHH502
B25: Asia | C25: Japan | D25: J. F. Oberlin University | E25: キャリアデザインD (LA・GC・健福-a) | F25: 201455 | G25: Định hướng nghề nghiệp | H25: TNHH502
B26: Asia | C26: Japan | D26: J. F. Oberlin University | E26: 国際マーケティング研究 | F26: 32112 | G26: Tiếng Nhật marketing quốc tế | H26: TNHH402
A27: 95 | B27: Asia | C27: Japan | D27: Kansai University | E27: International Business Communication | G27: Viết 3 | H27: TAN304 | I27: TC | J27: TATM
A28: chưa xác nhận tương đương | B28: Asia | C28: Japan | D28: Kansai University | E28: Japanese Economy (Topics in Japanese Economy and Discussion) | F28: 00705 | G28: Tiếng Nhật kinh tế | H28: TNHH303 | I28: CLC | J28: Tiếng Nhật
A29: chưa có link đính kèm | B29: Asia | C29: Japan | D29: Kansai University | E29: Japanese Industries and Companies (The Global Competition) | F29: 00687 | G29: Không tương đương với môn Tiếng Nhật kinh tế | H29: TNHH303 | I29: CLC | J29: Tiếng Nhật
A30: 84 | B30: Asia | C30: Japan | D30: Kansai University | E30: 経営学 | F30: 70352 | G30: Không tương đương môn thuộc khoa QTKD
B31: Asia | C31: Japan | D31: Kansai University | E31: International Business for Entrepreneurs | F31: 00680 | G31: Không tương đương với học phần English for Specific Purpose 5 (Public speaking)
B32: Asia | C32: Japan | D32: Kansai University | E32: Communication in Japanese Society (Business Japanese) | F32: 05132 | G32: Tiếng Nhật thương mại trung cấp 3,4 | H32: TNHH206, TNHH207
B33: Asia | C33: Japan | D33: Kansai University | E33: Communication in Japanese Society (Business Japanese) | F33: 05132 | G33: Tiếng Nhật thương mại trung cao cấp 1,2 | H33: TNHH301, TNHH302
B34: Asia | C34: Japan | D34: Kansai University | E34: International Political Economy 2 | F34: 30719 | G34: Không tương đương với học phần Pháp luật thương mại và kinh doanh quốc tế
B35: Asia | C35: Japan | D35: Kansai University | E35: International Business for Entrepreneurs | F35: 00680 | G35: Không tương đương Xây dựng dự án kinh doanh
B36: Asia | C36: Japan | D36: Kansai University | E36: 国際経済学２ | F36: 30628 | G36: Không tương đương với học phần Tiếng Nhật Kinh doanh Quốc tế
B37: Asia | C37: Japan | D37: Kansai University | E37: 経済学特殊講義１(実験で学ぶ経済学ー実験経済入門ー) | F37: 30730 | G37: Tiếng Nhật kinh tế | H37: TNHH303
B38: Asia | C38: Japan | D38: Kansai University | E38: 国際金融論 1 | F38: 30706 | G38: Không tương đương với học phần Tài chính quốc tế | J38: Khoa Tài chính ngân hàng
B39: Asia | C39: Japan | D39: Kansai University | E39: Communication in Japanese Society (Business Japanese) | F39: 05312 | G39: Không tương đương với học phần Tiếng nhật thương mại trung cấp 3
B40: Asia | C40: Japan | D40: Kansai University | E40: Communication in Japanese Society (Business Japanese) | F40: 05312 | G40: Không tương đương với học phần Tiếng nhật thương mại trung cấp 4
B41: Asia | C41: Japan | D41: Kansai University | E41: Communication in Japanese Society (Business Japanese) | F41: 05312 | G41: Không tương đương với học phần Tiếng nhật thương mại trung cao cấp 1
B42: Asia | C42: Japan | D42: Kansai University | E42: Communication in Japanese Society (Business Japanese) | F42: 05312 | G42: Không tương đương với học phần Tiếng nhật thương mại trung cao cấp 2
A43: 2 | B43: Asia | C43: Japan | D43: Kansai University | E43: 国際金融論 1 | F43: 30706 | G43: Không tương đương với học phần Tài chính quốc tế
B44: Asia | C44: Japan | D44: Kansai University | E44: DPsychology of Disaster Risks | F44: 95614 | G44: Không tương đương với học phần Tâm lý học Psychology mã TLHH202
B45: Asia | C45: Japan | D45: Kansai University | E45: Critical Thinking Skills | G45: Logics and Methodology of Studying and Research (Logic học và phương pháp nghiên cứu khoa học) | H45: TRIH201
A46: 86 | B46: Asia | C46: Japan | D46: Kibi International University | E46: Cross Cultural Understandings | F46: FS-FS-1-608
A47: 92 | B47: Asia | C47: Japan | D47: Kobe University | E47: Global Marketing | F47: 29402 | G47: Maketing trong kinh doanh quốc tế | H47: MKTH 306
B48: Asia | C48: Japan | D48: Kobe University | E48: International Economy and Finance | G48: Tài chính quốc tế | H48: TCHH414 | I48: CLC | J48: TCNH
A49: 97 | B49: Asia | C49: Japan | D49: Kwansei Gakuin University (KGU) | E49: 会話 * 聴解 (Level 5) | F49: 515405 | G49: Không tương đương
A50: 98 | B50: Asia | C50: Japan | D50: Kwansei Gakuin University (KGU) | E50: 口頭表現 (Level 6-8) | F50: 515625
A51: 100 | B51: Asia | C51: Japan | D51: Kwansei Gakuin University (KGU) | E51: 日本のビジネスA | F51: 46468000 | G51: Không có môn tương đương
B52: Asia | C52: Japan | D52: Musashino University | E52: Cross - cultural Communication A | F52: GS121 | G52: Intercultural Communication | H52: TAN112E
B53: Asia | C53: Japan | D53: Meiji University | E53: 日本語8（文章表現） | F53: (JE)LAN181J | G53: Viết II | H53: TNH310 | J53: gửi ngày 19/10/2023
A54: 112 | B54: Asia | C54: Japan | D54: Meiji University (School of Political Science and Economics) | E54: 貿易商務論Ａ | F54: (CO)ECN391J | G54: NNKTTM1: Quan hệ Kinh tế quốc tế | H54: TNH402 | I54: Tiêu chuẩn | J54: Tiếng Nhật
A55: 114 | B55: Asia | C55: Japan | D55: Mie University | E55: Lecture Course in Understanding Japan 3A | G55: Văn hoá văn minh Nhật Bản | H55: TNH315 | I55: Tiêu chuẩn | J55: Tiếng Nhật
A56: 115 | B56: Asia | C56: Japan | D56: Mie University | E56: Lecture Course in Understanding Japan 3A | G56: Xã hội Nhật Bản | H56: TNHH210 | I56: CLC | J56: Tiếng Nhật
B57: Asia | C57: Japan | D57: Mie University | E57: Listening and Conversation B | G57: Không tương đương với môn Nghe hiểu II
A58: 128 | B58: Asia | C58: Japan | D58: Momoyama Gakuin University | E58: Statistical Analysis of the Present- Day Japanese Economy | G58: Không tương đương với học phần Nguyên lý thống kê kinh tế
A59: 117 | B59: Asia | C59: Japan | D59: Momoyama Gakuin University | E59: ミクロ経済学 | G59: Ngôn ngữ KTTM 2: Kinh tế học | H59: TNH413 | I59: Tiêu chuẩn | J59: Tiếng Nhật
A60: 118 | B60: Asia | C60: Japan | D60: Momoyama Gakuin University | E60: ミクロ経済学 | G60: Tiếng Nhật kinh tế | H60: TNHH303 | I60: CLC | J60: Tiếng Nhật
B61: Asia | C61: Japan | D61: Momoyama Gakuin University | E61: ミクロ経済学 | G61: Ngôn ngữ kinh tế thương mại 9: Kinh tế học | H61: TNH413
A62: 46 | B62: Asia | C62: Japan | D62: Momoyama Gakuin University | E62: 日本語レベル C | G62: Không tương đương với học phần Đọc hiểu II
A63: 47 | B63: Asia | C63: Japan | D63: Momoyama Gakuin University | E63: 日本語レベル C | G63: Không tương đương với học phần Viết II
A64: Chưa có chữ ký của trưởng bộ môn | B64: Asia | C64: Japan | D64: Momoyama Gakuin University | E64: 学科特殊講義 - 中級中国語 I | F64: CULT3440 | G64: Không tương đương với học phần Ngoại ngữ 2 - Phần 2 (Tiếng Trung)
A65: Chưa tick tương đương/không tương đương | B65: Asia | C65: Japan | D65: Nagoya City University | E65: International Trade, Trade Policy | G65: Chính sách thương mại quốc tế
A66: Chưa có chữ ký của trưởng bộ môn | B66: Asia | C66: Japan | D66: Nagoya City University | E66: ファイナンス 分析 | F66: EGHU0003 | G66: Không tương đương với học phần Tiếng Nhật tài chính quốc tế
A67: Thiếu mô tả môn | B67: Asia | C67: Japan | D67: Nagoya City University | E67: ミクロ経済学 | G67: Ngôn ngữ KTTM 2: Kinh tế học | H67: TNH413 | I67: Tiêu chuẩn | J67: Tiếng Nhật | K67: Nguyễn Thị Bích Huệ
A68: Thiếu mô tả môn | B68: Asia | C68: Japan | D68: Nagoya City University | E68: ミクロ経済学 | G68: Tiếng Nhật kinh tế | H68: TNHH303 | I68: CLC | J68: Tiếng Nhật | K68: Nguyễn Thị Bích Huệ
A69: Thiếu mô tả môn | B69: Asia | C69: Japan | D69: Nagoya City University | E69: 入門経済学I | G69: Ngôn ngữ KTTM 2: Kinh tế học | H69: TNH413 | I69: Tiêu chuẩn | J69: Tiếng Nhật | K69: Nguyễn Thị Bích Huệ
A70: Thiếu mô tả môn | B70: Asia | C70: Japan | D70: Nagoya City University | E70: 入門経済学I | G70: Tiếng Nhật kinh tế | H70: TNHH303 | I70: CLC | J70: Tiếng Nhật | K70: Nguyễn Thị Bích Huệ
A71: Thiếu chữ ký trưởng bộ môn | B71: Asia | C71: Japan | D71: Nagoya City University | E71: マーケティングリサーチ | F71: EGMA0004 | G71: Không tương đương môn Tiếng Nhật Marketing Quốc tế
A72: Thiếu chữ ký trưởng bộ môn | B72: Asia | C72: Japan | D72: Nagoya City University | E72: ファイナンス分析 | F72: EGHU0003 | G72: Không tương đương với học phần Tiếng Nhật tài chính quốc tế
A73: Thiếu chữ ký trưởng bộ môn | B73: Asia | C73: Japan | D73: Nagoya City University | E73: 財政学 | F73: EGZA0006 | G73: Ngôn ngữ thương mại kinh tế 6: Tài chính kế toán | H73: TNH410 | I73: Tiêu chuẩn | J73: Tiếng Nhật
A74: Không tìm thấy | B74: Asia | C74: Japan | D74: Nagoya City University | E74: 日本語ディスカッション1 | F74: KGNI0101 | G74: Nói II | H74: TNH308 | I74: Tiêu chuẩn | J74: Tiếng Nhật
B75: Asia | C75: Japan | D75: Nagoya City University | E75: 日本語プレゼンテーション2 日本語プレゼンテーション1 | F75: KGNI0104 KGNI0103 | G75: Nói I | H75: TNH307 | I75: Tiêu chuẩn | J75: Tiếng Nhật
B76: Asia | C76: Japan | D76: Nagoya City University | E76: 日本語プレゼンテーション2 日本語プレゼンテーション1 | F76: KGNI0104 KGNI0103 | G76: Nói II | H76: TNH308 | I76: Tiêu chuẩn | J76: Tiếng Nhật
B77: Asia | C77: Japan | D77: Nagoya City University | E77: 日本語ライティング2 日本語ライティング1 | F77: KGNI0106 KGNI0105 | G77: Viết II | H77: TNH310 | I77: Tiêu chuẩn | J77: Tiếng Nhật
B78: Asia | C78: Japan | D78: Nagoya City University | E78: 日本語ライティング2 日本語ライティング1 | F78: KGNI0106 KGNI0105 | G78: Viết I | H78: TNH309 | I78: Tiêu chuẩn | J78: Tiếng Nhật
B79: Asia | C79: Japan | D79: Nagoya City University | E79: 日本語リーディング・リスニング2 日本語リーディング・リスニング1 | F79: KGNI0108 KGNI0107 | G79: Nghe hiểu I | H79: TNH303 | I79: Tiêu chuẩn | J79: Tiếng Nhật
B80: Asia | C80: Japan | D80: Nagoya City University | E80: 日本語リーディング・リスニング2 日本語リーディング・リスニング1 | F80: KGNI0108 KGNI0107 | G80: Nghe hiểu II | H80: TNH304 | I80: Tiêu chuẩn | J80: Tiếng Nhật
B81: Asia | C81: Japan | D81: Nagoya City University | E81: 日本語リーディング・リスニング2 日本語リーディング・リスニング1 | F81: KGNI0108 KGNI0107 | G81: Đọc hiểu II | H81: TNH306 | I81: Tiêu chuẩn | J81: Tiếng Nhật
B82: Asia | C82: Japan | D82: Nagoya City University | E82: 日本語リーディング・リスニング2 日本語リーディング・リスニング1 | F82: KGNI0108 KGNI0107 | G82: Nghe hiểu II | H82: TNH304 | I82: Tiêu chuẩn | J82: Tiếng Nhật
B83: Asia | C83: Japan | D83: Nagoya City University | E83: 日本語リーディング・リスニング2 日本語リーディング・リスニング1 | F83: KGNI0108 KGNI0107 | G83: Đọc hiểu I | H83: TNH305 | I83: Tiêu chuẩn | J83: Tiếng Nhật
B84: Asia | C84: Japan | D84: Nagoya City University | E84: 日本語リーディング・リスニング2 日本語リーディング・リスニング1 | F84: KGNI0108 KGNI0107 | G84: Nghe hiểu I | H84: TNH303 | I84: Tiêu chuẩn | J84: Tiếng Nhật
A85: 151 | B85: Asia | C85: Japan | D85: Nagoya University (NUPACE) | E85: Business Administration | F85: EGKE0008 | G85: Đang chờ xét môn Quản trị kinh doanh
B86: Asia | C86: Japan | D86: Nagoya University (NUPACE) | E86: Financial Accounting | F86: EGZA0012 | G86: Đang chờ xét môn Tài chính kế toán
A87: Chưa tick môn tương đương + thiếu mô tả môn | B87: Asia | C87: Japan | D87: Nara Women University (NWU) | E87: 日本事情A | F87: 0124000 | G87: Văn học Nhật Bản | H87: TNH211 | I87: Tiêu chuẩn | J87: Tiếng Nhật | K87: Phạm Quang Hưng
A88: Thiếu mô tả môn | B88: Asia | C88: Japan | D88: Osaka University of Economics (OUE) | E88: 経済学入門 | F88: 22386 | G88: Không tương đương với học phần Quản trị học | J88: Khoa Quản trị kinh doanh | K88: Ngô Quý Nhâm
A89: Thiếu mô tả môn | B89: Asia | C89: Japan | D89: Osaka University of Economics (OUE) | E89: 国際貿易論 | F89: 53261 | G89: Không tương đương với học phần Giao dịch thương mại quốc tế | J89: Viện Kinh tế và Kinh doanh quốc tế | K89: Phan Thị Thu Hiền
A90: Không tìm thấy môn | B90: Asia | C90: Japan | D90: Osaka University of Economics (OUE) | E90: 経済理論基礎 | F90: 41116/ 42391 | G90: Đang chờ xét duyệt với học phần Tiếng Nhật kinh tế và Ngôn ngữ Kinh tế thương mại 9: Kinh tế học
A91: Thiếu mô tả môn | B91: Asia | C91: Japan | D91: Osaka University of Economics (OUE) | E91: 経営学基礎 | F91: 32556/ 41146 | G91: Không tương đương với học phần Quản trị học | J91: Khoa Quản trị kinh doanh | K91: Ngô Quý Nhâm
A92: Không tìm thấy môn | B92: Asia | C92: Japan | D92: Osaka International University (OIU) | E92: International Business Laws | F92: 26111 | G92: Đang chờ xét duyệt môn Pháp luật thương mại và kinh doang quốc tế (sai phiếu xét)
A93: Không tìm thấy môn | B93: Asia | C93: Japan | D93: Sophia University | E93: Marketing | G93: Marketing căn bản | H93: MKT301/MKTE302 | J93: KDQT, KTĐN, QTKD, TMQT, Digital Marketing, TCNH
A94: Chưa có chữ ký của trưởng bộ môn | B94: Asia | C94: Japan | D94: Sophia University | E94: Venture Management | F94: IBE457 | G94: Không tương đương với học phần Entrepreneurship and Innovation | J94: Tài chính ngân hàng
A95: Không tìm thấy môn | B95: Asia | C95: Japan | D95: Sophia University | E95: Human Resource Management | F95: AIBE3200 | G95: Quản trị nguồn nhân lực | H95: QTR403, QTRE403 | I95: Tiêu chuẩn, CLC
A96: Không tìm thấy môn | C96: Japan | D96: Sophia University | E96: Public Speaking | F96: AENG115A | G96: Đang chờ xét duyệt môn English for Specific Purpose 5 (Public Speaking) (gửi khoa TATM ngày 21/9)
A97: Không tìm thấy môn | B97: Asia | C97: Japan | D97: Sophia University | E97: Financial Accounting 1 | F97: EMGS5004 | G97: Nguyên lý kế toán | H97: KET201E, KETE201
A98: Không tìm thấy môn | B98: Asia | C98: Japan | D98: Sophia University | E98: Principles of Management | F98: AIBE3000 | G98: Không tương đương học phần Những nguyên lý về quản trị và vận hành
A99: Không tìm thấy môn | B99: Asia | C99: Japan | D99: Sophia University | E99: Strategic Management | F99: EMGS5037 | G99: Quản trị chiến lược | H99: QTR312E, QTR312, QTRE312
A100: Không tìm thấy môn | B100: Asia | C100: Japan | D100: Sophia University | E100: Entrepreneurship 1 | F100: EMGS5052 | G100: Khởi sự kinh doanh | H100: QTR309E; QTR309; QTRE309
A101: Thiếu chữ ký của trưởng bộ môn | B101: Asia | C101: Japan | D101: University of Fukui | E101: Spartial Data Analysis | G101: Không tương đương với môn Cơ sở dữ liệu
A102: Không tìm thấy môn | B102: Asia | C102: Japan | D102: Rikkyo University | E102: Marketing Management ịn Japan | F102: BT161 | G102: Không tương đương với học phần Thương hiệu trong kinh doanh quốc tế
A103: Không tìm thấy môn | B103: Asia | C103: Japan | D103: Rikkyo University | E103: Marketing Management ịn Japan | F103: BT161 | G103: Marketing căn bản | H103: MKTE301
...

Sheet Rà soát lại
B1: Châu | C1: Nước | D1: Trường đối tác | E1: Tên môn tại trường đối tác | F1: Mã môn tại trường đối tác | G1: Tên môn tại FTU | H1: Mã môn tại FTU | I1: Chương trình | J1: Khoa/Chuyên ngành
B2: Asia | C2: Japan | D2: Doshisha Women's College of Liberal Arts (DWCLA) | E2: Japanese Composition II A | F2: 245760 | G2: Đang xét duyệt với Viết II (Gửi lại 21.08)
B3: Asia | C3: Japan | D3: Doshisha Women's College of Liberal Arts (DWCLA) | E3: Japanese Reading Comprehension II A | F3: 245360 | G3: Đang xét duyệt với Đọc II (Gửi lại 21.08) | H3: TNH306 | I3: Tiêu chuẩn | J3: Tiếng Nhật
B4: Asia | C4: Japan | D4: Hiroshima University of Economics | E4: 交換留学日本語（上級AI | F4: 36027 | G4: Ngoại ngữ 4 | H4: TNH232 | I4: Tiêu chuẩn | J4: KTĐN
B5: Asia | C5: Japan | D5: Hiroshima University of Economics | E5: 交換留学日本語（上級AI | F5: 36027 | G5: Ngoại ngữ 5 | H5: TNH331 | I5: Tiêu chuẩn | J5: KTĐN
B6: Asia | C6: Japan | D6: Hiroshima University of Economics | E6: 交換留学日本語（上級BI | F6: 36029 | G6: Ngoại ngữ 4 | H6: TNH232 | I6: Tiêu chuẩn | J6: KTĐN
B7: Asia | C7: Japan | D7: Hiroshima University of Economics | E7: 交換留学日本語（上級BI | F7: 36029 | G7: Ngoại ngữ 5 | H7: TNH331 | I7: Tiêu chuẩn | J7: KTĐN
B8: Asia | C8: Japan | D8: Hiroshima University of Economics | E8: International management | G8: Không tương đương với Business and economic project practices
B9: Asia | C9: Japan | D9: Hiroshima University of Economics | E9: Practical Management Theory | G9: Không tương đương với Business and economic project practices
B10: Asia | C10: Japan | D10: Hitotsubashi University | E10: 日本語中上級(漢字語彙) | G10: Từ vựng tiếng Nhật nâng cao | H10: TNH226 | I10: Tiêu chuẩn | J10: Tiếng Nhật
B11: Asia | C11: Japan | D11: Hitotsubashi University | E11: Corporate Finance | G11: Không tương đương với học phần Tài chính Quốc tế
B12: Asia | C12: Japan | D12: Hitotsubashi University | E12: Advanced Corporate Finance | F12: 1BE43601 | G12: Không tương đương với học phần Tài chính Quốc tế
B13: Asia | C13: Japan | D13: Hitotsubashi University | E13: 経済の日上級II(留学生用） | G13: Đọc thương mại | H13: TNHH205 | I13: CLC | J13: Tiếng Nhật
B14: Asia | C14: Japan | D14: Hitotsubashi University | E14: 日本語上級 (読解) I | F14: 1GE24202 | G14: Không tương đương với Đọc thương mại
B15: Asia | C15: Japan | D15: Hitotsubashi University | E15: ビジネス・コミュニケーション… | G15: Không tương đương với Nghe - đọc thương mại 1
B16: Asia | C16: Japan | D16: Hitotsubashi University | E16: ビジネス・コミュニケーション… | G16: Không tương đương với Nghe - đọc thương mại 2
B17: Asia | C17: Japan | D17: Hitotsubashi University | E17: 経官戦略論 | G17: Đang chờ xét duyệt môn Kinh doanh quốc tế | H17: KDOH307 | I17: CLC | J17: Tiếng Nhật
B18: Asia | C18: Japan | D18: Hitotsubashi University | E18: Special Topics on Management and Marketing | F18: 1BB38501 | G18: Kỹ năng lãnh đạo và phát triển cá nhân | H18: QTRE203; QTR203; QTR203E
B19: Asia | C19: Japan | D19: Hitotsubashi University | E19: Intermediate Course in Management | F19: 1BB27801 | G19: Hành vi tổ chức | H19: QTRE402; QTR402; QTR402E
B20: Asia | C20: Japan | D20: Hitotsubashi University | E20: Special Topics on Management and Marketing | F20: 1BB38501 | G20: Đạo đức kinh doanh | H20: QTR305E; QTR305; QTRE305
B21: Asia | C21: Japan | D21: Hitotsubashi University | E21: Interactive Course on Business Basics (Finance) | F21: 1BB27601 | G21: Khoa đề xuất tương đương với học phần Quản trị tài chính doanh nghiệp (KET307) tuy nhiên cần bổ sung giải thích credit của trường Hitotsubashi
B22: Asia | C22: Japan | D22: J. F. Oberlin University | E22: 異文化経営論 | F22: 262077 | G22: Quản trị đa văn hóa | H22: QTRH408
B24: Asia | C24: Japan | D24: Kansai University | E24: International Business Communication | G24: Không tương đương với môn Ngôn ngữ kinh tế thương mại 3: Giao tiếp kinh doanh | H24: TAN407 | I24: TC | J24: TATM
B25: Asia | C25: Japan | D25: Kansai University | E25: International Business Communication | G25: Viết 3 | H25: TAN304 | I25: TC | J25: TATM
B26: Asia | C26: Japan | D26: Kansai University | E26: Japanese Industries and Companies (The Global Competition) | F26: 00687 | G26: Không tương đương với môn Tiếng Nhật kinh tế | H26: TNHH303 | I26: CLC | J26: Tiếng Nhật
B27: Asia | C27: Japan | D27: Kansai University | E27: 経営学 | F27: 70352 | G27: Không tương đương môn thuộc khoa QTKD
B28: Asia | C28: Japan | D28: Kansai University | E28: International Business Communication | G28: Không tương đương môn Ngôn ngữ Kinh tế thương mại 3: Giao tiếp Kinh doanh | H28: TAN407 | I28: CTTC | J28: TATM
B29: Asia | C29: Japan | D29: Kansai University | E29: KUGF Independent Study (Doing a Research) | F29: 00875 | G29: Viết 3 | H29: TAN304 | I29: CTTT | J29: TATM
B30: Asia | C30: Japan | D30: Kansai University | E30: Global Awareness II | F30: 00680 | G30: Không tương đương với học phần Global Governance
B31: Asia | C31: Japan | D31: Kansai University | E31: Global Awareness II | F31: 00882 | G31: không tương đương với môn Business Ethics and Corporate Social responsibility
B32: Asia | C32: Japan | D32: Kansai University | E32: International Political Economy 2 | F32: 30719 | G32: Đang chờ xét duyệt môn Pháp luật thương mại và kinh doanh quốc tế
B33: Asia | C33: Japan | D33: Kansai University
B34: Asia | C34: Japan | D34: Kansai University
B35: Asia | C35: Japan | D35: Kansai University | E35: Critical Thinking Skills | G35: Logics and Methodology of Studying and Research (Logic học và phương pháp nghiên cứu khoa học) | H35: TRIH201
B36: Asia | C36: Japan | D36: Kobe University | E36: Global Marketing | F36: 29402 | G36: Maketing trong kinh doanh quốc tế | H36: MKTH 306
B37: Asia | C37: Japan | D37: Kwansei Gakuin University | E37: 会計学基礎 | F37: 34149000 | G37: Ngôn ngữ kinh tế thương mại 6: Tài chính kế toán | H37: TNH410 | I37: TC
B38: Asia | C38: Japan | D38: Kwansei Gakuin University | E38: 経営学 A | F38: 254820 | G38: Ngôn ngữ kinh tế thương mại 8: Quản trị kinh doanh | H38: TNH412
B39: Asia | C39: Japan | D39: Musashino University | E39: Finance B | F39: GBS242 | G39: Tài chính doanh nghiệp | H39: TCH321, TCHE321
B43: Asia | C43: Japan | D43: Meiji University | E43: 国際経済学Ａ | F43: (CO)ECN391J | G43: Đang xét với học phần Ngôn ngữ kinh tế thương mại 1: Quan hệ kinh tế quốc tế | J43: gửi ngày 19/10/2023
B44: Asia | C44: Japan | D44: Meiji University | E44: 日本語7（語彙・文型表現) | F44: (JE)LAN181J | G44: Đang xét với học phân Ngữ pháp tiếng Nhật nâng cao | J44: gửi ngày 19/10/2023
B45: Asia | C45: Japan | D45: Meiji University | E45: 日本語6（読解） | F45: (JE)LAN181J | G45: Đang xét với học phần Đọc hiểu II | J45: gửi ngày 19/10/2023
B46: Asia | C46: Japan | D46: Meiji University | E46: 日本語6（文章表現） | F46: (JE)LAN181J | G46: Đang xét với học phần Viết II | J46: gửi ngày 19/10/2023
B47: Asia | C47: Japan | D47: Meiji University | E47: 会計学総論A | F47: (C O )ACC231J | G47: Đang xét với học phần Ngôn ngữ kinh tế thương mại 6: Tài chính kế toán | J47: gửi ngày 19/10/2023
B48: Asia | C48: Japan | D48: Meiji University | E48: 日本語7（語彙・文型表現) | F48: (JE)LAN181J | G48: Không tương đương với học phần Ngữ pháp tiếng Nhật nâng cao | H48: TNH227
B49: Asia | C49: Japan | D49: Meiji University | E49: 日本語7（語彙・文型表現) | F49: (JE)LAN181J | G49: Từ vựng tiếng Nhật nâng cao | H49: TNH226
B50: Asia | C50: Japan | D50: Meiji University | E50: 日本事情 | F50: (BA)IND111J | G50: Văn hóa văn minh Nhật Bản | H50: TNH315
B51: Asia | C51: Japan | D51: Meiji University | E51: 日本語6（読解） | F51: (JE)LAN181J | G51: Đọc hiểu II | H51: TNH306
B52: Asia | C52: Japan | D52: Meiji University | E52: 日本語6（文章表現） | F52: (JE)LAN181J | G52: Không tương đương với học phần Viết II
B53: Asia | C53: Japan | D53: Meiji University | E53: 会計学総論A | F53: (CO)ACC231J | G53: NNKTTM 6: Tài chính kế toán | H53: TNH410
B54: Asia | C54: Japan | D54: Meiji University | E54: 貿易商務論Ａ | F54: (CO)CMM351J | G54: NNKTTM 3: Giao dịch thương mại | H54: TNH404
B55: Asia | C55: Japan | D55: Meiji University | E55: 国際ビジネス交渉論Ａ | F55: (CO)CMM391J | G55: Không tương đương với học phần NNKTTM 2: Đàm phán thương mại
B56: Asia | C56: Japan | D56: Meiji University | E56: 国際経済学Ａ | F56: (CO)ECN391J | G56: NNKTTM 1: Quan hệ kinh tế quốc tế | H56: TNH402
B57: Asia | C57: Japan | D57: Mie University | E57: 日本の文学 A | G57: Không tương đương với Văn học Nhật bản
B58: Asia | C58: Japan | D58: Momoyama Gakuin University | E58: Problems in labor economics | G58: Không tương đương
B59: Asia | C59: Japan | D59: Momoyama Gakuin University | E59: 簿記[2] 02<春> | G59: Ngôn ngữ kinh tế thương mại 6:Tài chính kế toán | H59: TNH410
B60: Asia | C60: Japan | D60: Momoyama Gakuin University | E60: Economics A (経済学 A) ECON1000 Economics B (経済学 B) ECON1000 | G60: Ngôn ngữ kinh tế thương mại 9: Kinh tế học | H60: TNH413
B61: Asia | C61: Japan | D61: Nagoya City University | E61: 日本語 | G61: Đọc hiểu II | H61: TNH306 | I61: Tiêu chuẩn | J61: Tiếng Nhật
B62: Asia | C62: Japan | D62: Nagoya City University | E62: 日本語 | G62: Nghe hiểu II | H62: TNH304 | I62: Tiêu chuẩn | J62: Tiếng Nhật
B63: Asia | C63: Japan | D63: Nagoya City University | E63: 日本語 | G63: Đọc hiểu I | H63: TNH305 | I63: Tiêu chuẩn | J63: Tiếng Nhật
B64: Asia | C64: Japan | D64: Nagoya City University | E64: 日本語 | G64: Nghe hiểu I | H64: TNH303 | I64: Tiêu chuẩn | J64: Tiếng Nhật
B65: Asia | C65: Japan | D65: Nagoya City University | E65: 入門経済学I | F65: EGNI0011 | G65: Tiếng Nhật kinh tế | H65: TNHH303 | I65: CLC | J65: Tiếng Nhật
B66: Asia | C66: Japan | D66: Nagoya City University | E66: Financial Accounting | F66: EGZA0012 | G66: Ngôn ngữ thương mại 6: Tài chính kế toán | H66: TNH410 | I66: TC | J66: Tiếng Nhật
B67: Asia | C67: Japan | D67: Nagoya City University | E67: Business Administration | F67: EGKE0008 | G67: Ngôn ngữ thương mại 8: Quản trị kinh doanh | H67: TNH412 | I67: TC | J67: Tiếng Nhật
B68: Asia | C68: Japan | D68: Nagoya City University | E68: 日本語・文化セミナー２ | F68: HGNI0072 | G68: Văn học Nhật Bản | H68: TNH211
B69: Asia | C69: Japan | D69: Nagoya City University | E69: 日本語・文化セミナー２ | F69: HGNI0072 | G69: Không tương đương với học phần Văn hóa và văn minh Nhật Bản
B70: Asia | C70: Japan | D70: Nagoya City University | E70: 日本語上級２ | F70: KGNI0059 | G70: Không tương đương với học phần Đọc hiểu II
B71: Asia | C71: Japan | D71: Nagoya City University | E71: 日本語上級２ | F71: KGNI0059 | G71: Không tương đương với học phần Nghe hiểu II
B72: Asia | C72: Japan | D72: Nagoya University (NUPACE) | E72: Business Administration | F72: EGKE0008 | G72: Đang chờ xét môn Quản trị kinh doanh
B73: Asia | C73: Japan | D73: Nagoya University (NUPACE) | E73: Financial Accounting | F73: EGZA0012 | G73: Đang chờ xét môn Tài chính kế toán
B74: Asia | C74: Japan
B75: Asia | C75: Japan | D75: Osaka University of Economics (OUE) | E75: 国際貿易論 | F75: 53261 | G75: Đang chờ xét duyệt với môn Tiếng Nhật giao dịch thương mại quốc tế
B76: Asia | C76: Japan | D76: Osaka University of Economics (OUE) | E76: 経済理論基礎 | F76: 42396 | G76: Đang chờ xét duyệt với học phần Tiếng Nhật kinh tế và Ngôn ngữ Kinh tế thương mại 9: Kinh tế học | J76: K. Tiếng Nhật
B77: Asia | C77: Japan | D77: Osaka University of Economics (OUE) | E77: 経済理論基礎 | F77: 41116/ 42391 | G77: Đang chờ xét duyệt với học phần Tiếng Nhật kinh tế và Ngôn ngữ Kinh tế thương mại 9: Kinh tế học
B78: Asia | C78: Japan | D78: Osaka University of Economics (OUE)
B79: Asia | C79: Japan | D79: Osaka University of Economics (OUE) | E79: 経営学入門 | F79: 22386 | G79: Không tương đương với học phần Quản trị học
B80: Asia | C80: Japan | D80: Osaka University of Economics (OUE)
B81: Asia | C81: Japan | D81: Osaka University of Economics (OUE) | E81: 経営学基礎 | G81: Không tương đương với học phần Quản trị học
B82: Asia | C82: Japan | D82: Osaka University of Economics (OUE) | E82: 国際貿易論 | G82: Đang xét với Giao dịch thương mại quốc tế
B83: Asia | C83: Japan | D83: Osaka University of Economics (OUE)
B84: Asia | C84: Japan | D84: Osaka International University (OIU) | E84: International Business Laws | F84: 26111 | G84: Đang chờ xét duyệt môn Pháp luật thương mại và kinh doang quốc tế
B85: Asia | C85: Japan | D85: Sophia University | E85: Human Resource Management | F85: AIBE3201 | G85: Human Resource Management | H85: QTRE403, QTR403E | I85: CLC, CTTT
B86: Asia | C86: Japan | D86: Sophia University | E86: Management Accounting | F86: AIBE3060 | G86: Không tương đương với học phần Corporate Finance
B87: Asia | C87: Japan | D87: Sophia University | E87: Public Speaking | F87: AENG115A | G87: Đang chờ xét duyệt môn English for Specific Purpose 5 (Public Speaking) (gửi khoa TATM ngày 21/9)
B88: Asia | C88: Japan | D88: Sophia University | E88: Financial Accounting 1 | F88: EMGS5004 | G88: Nguyên lý kế toán | H88: KET201E, KETE201
B89: Asia | C89: Japan | D89: Sophia University | E89: Principles of Management | F89: AIBE3000 | G89: Không tương đương học phần Những nguyên lý về quản trị và vận hành
B90: Asia | C90: Japan | D90: Sophia University | E90: Strategic Management | F90: EMGS5037 | G90: Quản trị chiến lược | H90: QTR312E, QTR312, QTRE312
B91: Asia | C91: Japan | D91: Sophia University | E91: Entrepreneurship 1 | F91: EMGS5052 | G91: Khởi sự kinh doanh | H91: QTR309E; QTR309; QTRE309
B93: Asia | C93: South Korea | D93: Seoul National University (SNU) | E93: Special Issues in Entrepreneurship and Innovation | G93: Đang xét duyệt với Khởi sự Kinh doanh (Gửi Khoa QTKD ngày 21.08)
B94: Asia | C94: South Korea | D94: Seoul National University (SNU) | E94: Marketing Management | G94: Không tương đương với môn Marketing căn bản & Marketing quốc tế | J94: Viện KT & KDQT
B95: Asia | C95: South Korea | D95: SolBridge International School of Business, Woosong University | E95: Brand Management Digital-Marketing Psychology for Business | F95: MKT403 MKT435A PSY201A | G95: Không có môn học tương đương
B96: Asia | C96: South Korea | D96: SolBridge International School of Business, Woosong University | E96: Introduction to Corporate Finance | F96: FIN305 | G96: Tài chính doanh nghiệp | H96: TCH321
B97: North America | C97: Canada | D97: University of Victoria | E97: Beginners' Spanish | F97: SPAN100A | G97: Không tương đương với học phần Tiếng Tây Ban Nha học thuật và thương mại 1
B98: North America | C98: Canada | D98: University of Victoria | E98: Financial Accounting | F98: COM202 | G98: Đang xét duyệt với Quản trị tài chính quốc tế (gửi ngày 26/9)
B99: North America | C99: Canada | D99: University of Victoria | E99: Financial Accounting I | F99: COM202 | G99: Đang xét duyệt với môn Nguyên lý kế toán | H99: KETE201 KET201 KET201E
B100: North America | C100: Canada | D100: University of Victoria | E100: Business English and Communication | G100: Ngôn ngữ KTTM3: Giao tiếp Kinh doanh | H100: TAN407 | I100: CTTC | J100: TATM
B101: North America | C101: Canada | D101: University of Victoria | E101: Business Analytics | F101: ECO231C | G101: Phân tích dữ liệu kinh doanh | H101: VJP205E | I101: CT CLC - CTTT | J101: Viện VJCC
B102: North America | C102: USA | D102: ATI College | E102: Project Management | F102: MG375 | G102: Không tương đương với học phần Quản trị dự án
B103: North America | C103: USA | D103: ATI College | E103: Introduction to communication
B104: North America | C104: USA | D104: Niagara University | E104: Public Speaking | F104: SPK101D | G104: Đang chờ xét duyệt với Tiếng Anh chuyên ngành 5 (Diễn thuyết trước công chúng) (gửi lại khoa TATM ngày 21/8) | H104: ESP451 | I104: CLC, Tiêu chuẩn
B105: North America | C105: USA | D105: Darla Moore School of Business, University of South Carolina | E105: Introduction to Financial Accounting | F105: ACCT225 | G105: Principles of Accounting | H105: KETE201
...

Sheet Stage 1 Nhập chờ hệ thống
A1: Ngày nhập hệ thống | B1: Châu | C1: Nước | D1: Trường đối tác | E1: Tên môn tại trường đối tác | F1: Mã môn tại trường đối tác | G1: Tên môn tại FTU | H1: Mã môn tại FTU | I1: Chương trình | J1: Khoa/Chuyên ngành
A2: 44938 | D2: Waseda Universitty | E2: Business Model Creation with AI Technologics beta (for undergraduate) | F2: MANX157L | G2: Thực hành Kinh doanh Quốc tế 1 | H2: KDOE410
A3: 44938 | D3: Waseda Universitty | E3: Communication Strategy English-based Undergraduate program | F3: LANE102E | G3: Tiếng anh chuyên ngành 5 | H3: ESP451
A4: 44938 | D4: Dankook University | E4: Corporate Finance | F4: 467220 | G4: Ngôn ngữ kinh tế Thương mại 5 - Tài chính | H4: TAN410
A5: 44938 | D5: Waseda Universitty | E5: Corporate Finance 1 | F5: 1600004AB3 | G5: Tài chính quốc tế | H5: TCHE414
A6: 44938 | D6: Waseda Universitty | E6: Corporate Finance 1 | F6: 1600004AB3 | G6: Tài chính công | H6: TCHE431
A7: 44938 | D7: Waseda Universitty | E7: English Plus (Public speaking and speech) 01 | F7: LANE303F | G7: Tiếng anh chuyên ngành 5 | H7: ESP451
A8: 44938 | D8: Waseda Universitty | E8: Entertainment Business Strategy | F8: MANX631L | G8: Kinh tế học cái hoạt dọng giải trí ngoài trời | H8: AREC346
A9: 44938 | D9: Yonsei University | E9: Financial Management | F9: MGT3016.01 - 01 | G9: Phân tích và đầu tư chứng khoán | H9: DTU401E
A10: 44938 | D10: Hasselt University | E10: Human Resource Management | F10: 3709 | G10: Human Resource Management | H10: QTR403E
A11: 44938 | D11: Hasselt University | E11: Human Resource Management | F11: 3709 | G11: Principles of economic management | H11: DTU301E
A12: 44938 | D12: University of Mannheim | E12: International Accounting | F12: ACC351 | G12: Kế toán quốc tế | H12: KETE410
A13: 44938 | D13: Friedrich Alexander University Erlangen-Nuremberg (FAU) | E13: International Economics | G13: Kinh tế quốc tế | H13: KTE308
A14: 44938 | D14: Friedrich Alexander University Erlangen-Nuremberg (FAU) | E14: International Economics | G14: Kinh tế quốc tế | H14: KTEE308
A15: 44938 | D15: Friedrich Alexander University Erlangen-Nuremberg (FAU) | E15: International Economics | G15: Kinh tế quốc tế | H15: KTE308E
A16: 44938 | D16: Friedrich Alexander University Erlangen-Nuremberg (FAU) | E16: International Finance | G16: Thị trường tài chính quốc tế
A17: 44938 | D17: Friedrich Alexander University Erlangen-Nuremberg (FAU) | E17: International Finance | G17: Thị trường tài chính quốc tế | H17: TCH403E
A18: 44938 | D18: Friedrich Alexander University Erlangen-Nuremberg (FAU) | E18: International Finance | G18: Thị trường tài chính quốc tế | H18: TCH403
A19: 44938 | D19: Waseda Universitty | E19: International Finance | F19: ECNA121L | G19: Tài chính quốc tế | H19: TCHHE414
A20: 44938 | D20: Waseda Universitty | E20: International Finance | F20: ECNA121L | G20: Tiền tệ_Ngân hàng | H20: TCHE303
A21: 44938 | D21: Waseda Universitty | E21: International Finance | F21: ECNA121L | G21: Quản trị tài chính_Lý thuyết và Ứng dụng | H21: FIN370
A22: 44938 | D22: Waseda Universitty | E22: International Finance | F22: ECNA121L | G22: Tài chính doanh nghiệp | H22: TCHE321
A23: 44938 | D23: Waseda Universitty | E23: International Finance | F23: ECNA121L | G23: Tài chính công | H23: TCHE431
A24: 44938 | D24: Dankook University | E24: International Management | F24: 319960 | G24: Ngôn ngữ Kinh tế Thương mại 2 - Kinh doanh Quốc tế | H24: TAN403
A25: 44938 | D25: Waseda Universitty | E25: Introduction to Language and Communication | F25: LNGT2015 | G25: Tiếng anh chuyên ngành 5 | H25: ESP451
A26: 44938 | D26: Dankook University | E26: Money and Banking | F26: 467290 | G26: Thanh toán quốc tế | H26: TCH412
A27: 44938 | D27: Waseda Universitty | E27: Money and Banking I(E) 01 | F27: ECNA221L | G27: Tiền tệ_Ngân hàng | H27: TCHE303
A28: 44938 | D28: Waseda Universitty | E28: Money and Banking I(E) 01 | F28: ECNA221L | G28: Tài chính doanh nghiệp | H28: TCHE321
A29: 44938 | D29: Waseda Universitty | E29: Money and Banking I(E) 01 | F29: ECNA221L | G29: Tài chính quốc tế | H29: TCHE414
A30: 44938 | D30: Waseda Universitty | E30: Money and Banking I(E) 01 | F30: ECNA221L | G30: Tài chính công | H30: TCHE431
A31: 44938 | D31: Waseda Universitty | E31: Social Business Cooperation Projects | F31: 18G0000146 | G31: Thực hành Kinh doanh Quốc tế 1 | H31: KDOE410
A32: 44938 | D32: Yokohama National University | E32: アカデミックライティング・プレゼンテーション | F32: J514 | G32: Viết thương mại | H32: TNHH305
A33: 44938 | D33: Yokohama National University | E33: 聴く・読む/ Listening and Reading | F33: J512 | G33: Nghe thương mại
A34: 44938 | D34: Yokohama National University | E34: 聴く・読む/ Listening and Reading | F34: J512 | G34: Đọc thương mại
A35: 44968 | D35: Kansai University | E35: Business for Sustainable Development Goals | G35: Social Innovation (Sáng tạo xã hội) | H35: TMAE202
A36: 44968 | D36: Kansai University | E36: Critical Thinking Skills | G36: Logics and Methodology of Study and Research (Logic học và phương pháp học tập, nghiên cứu của khoa học | H36: TRIH200
A37: 44968 | D37: Hannam University | E37: Financial Investment | F37: 25726 | G37: Financial Management in Hospitality | H37: QKSE402
A38: 44968 | D38: University of Augsburg | E38: International Accounting | F38: WIW - 0268 | G38: Kế toán quản trị | H38: KET310E
A39: 44968 | D39: Hasselt University | E39: International Business | F39: 3884 | G39: International Business Communication | H39: MKT408E
A40: 44968 | D40: Neu-Ulm university of Applied Science | E40: International Business | F40: 1282320 | G40: Quản trị & kinh doanh quốc tế (International business & management) | H40: QTRE401
A41: 44968 | D41: Kansai University | E41: International Business for Entrepreneurs | F41: 00680 | G41: Innovation (Đổi mới sáng tạo) | H41: TMAE319
A42: 44968 | D42: Hochschule Trier | E42: International Economics | F42: 41992 | G42: International Trade Policy | H42: TMA301E
A43: 44968 | D43: LUISS University | E43: International Financial Economics | F43: M247 | G43: Kinh tế học tài chính (Financial Economics) | H43: TCHE341
A44: 44968 | D44: Ossnabriick University of Applied Sciences | E44: Management Concepts | F44: 22B0922 | G44: Quản trị học | H44: QTRE303
A45: 44968 | D45: LUISS Guido Carli | E45: Managerial Accounting, Planning and Control | F45: BA013 | G45: Kế toán quản trị | H45: KET310E
A46: 44968 | D46: LUISS Guido Carli | E46: Managerial Economics | F46: M272IN | G46: Kinh tế học quản lý | H46: KTE312E
A47: 44968 | D47: Hochschule Trier | E47: Operations Management | F47: 41990 | G47: Logics and International Transactions | H47: TMA305E | I47: Nội dung học phần không chi tiết, đề nghị sinh viên in lại mô tả môn vì 2 mặt nội dung là 2 môn khác nhau
A48: 44968 | D48: Hochschule Trier | E48: Operations Managements | F48: 41990 | G48: Supply Chain Managements | H48: TMA313E | I48: Nội dung học phần không chi tiết, đề nghị sinh viên in lại mô tả môn vì 2 mặt nội dung là 2 môn khác nhau
A49: 44968 | D49: Yonsei University | E49: Organizational Behavior | F49: MGT2007-02 | G49: Tiêu chuẩn đạo đức hành nghề và QTDN | H49: DTU304 DTUE304 DTU304E
A50: 44968 | D50: Yonsei University - Mirae Campus | E50: Organizational Behavior | F50: EIC3224-01 MGT2007-01 | G50: Tiêu chuẩn đạo đức hành nghề và quản trị doanh nghiệp | H50: DTU304E DTU304
A51: 44968 | D51: University of Augsburg | E51: Systematic Creativity | F51: WIW - 0367 | G51: Sáng tạo xã hội | H51: TMA202E
A52: 18/03/2024 | D52: Meiji University | E52: 7 | F52: (JE) LAN181J | G52: Viết II | H52: TNH310
A53: 18/03/2024 | D53: Meiji University | E53: 8 | F53: (JE) LAN181J | G53: Viết II | H53: TNH310
A54: 18/03/2024 | D54: _x0008_Luiss University | E54: Corporate Finance | F54: T045 | G54: Tài chính doanh (Corporate Finance) | H54: TCH321E
A55: 18/03/2024 | D55: Handong Global University | E55: Cost & Management Accounting | F55: MEC30066 | G55: Kế toán quản trị | H55: KET310
A56: 18/03/2024 | D56: _x0008_Luiss University | E56: Ethical Standards & Practices in Finance | F56: SMDEFCFA | G56: Tiêu chuẩn đạo đức, hành nghề & quản trị doanh nghiệp | H56: DTU304E
A57: 18/03/2024 | D57: Handong Global University | E57: Financial Management | F57: GMP30002 | G57: Tài chính doanh nghiệp | H57: TCH321
A58: 18/03/2024 | D58: SolBridge International School of Business, Woosong University | E58: Human Resource Management | F58: BUS410B | G58: Quản trị nguồn nhân lực | H58: QTRE403
A59: 18/03/2024 | D59: Rikkyo University | E59: International Business Law A | F59: EX106 | G59: Pháp luật kinh doanh quốc tế | H59: PLU410E
A60: 18/03/2024 | D60: Pukyong National University (PKNU) | E60: International Financial Management | F60: 101050 | G60: Quản trị tài chính quốc tế | H60: _x001d_TCHE425
A61: 18/03/2024 | D61: Handong Global University | E61: Introduction to Management | F61: MEC10002 | G61: _x0008_Khoa học quản lí cơ bản | H61: KD0202
A62: 18/03/2024 | D62: _x0008_Rikkyo University | E62: Marketing Research | F62: OW447 | G62: Phương pháp nghiên cứu trong kinh tế và kinh doanh (Research Methodology for Economics and Business) | H62: KTE206E
A63: 18/03/2024 | D63: Luiss University | E63: Statistics for Business Studies A | F63: BA06 | G63: Lý thuyết xác suất và thống kê toán | H63: TOA201E
A64: 18/03/2024 | D64: Musashino University | E64: Statistics for Business Studies A | F64: GBS351 | G64: Statistics and Business Analysis | H64: TOA308E
A65: 18/03/2024 | D65: _x0008_Nagoya City University | E65: 日本語上級２ | F65: KGNI0059 | G65: Đọc hiểu I | H65: TNH305
A66: 18/03/2024 | D66: _x0008_Nagoya City University | E66: 経営管理 | F66: EGKE0051
A67: 25/6/2024
A68: 25/6/2024 | D68: Minnesota State University | E68: Advanced Corporate Finance | F68: FINA461 | G68: Ứng dụng công nghệ thông tin trong tài chính ngân hàng | H68: NHAE408
A69: 25/6/2024 | D69: Minnesota State University | E69: Advanced Corporate Finance | F69: FINA461 | G69: Tài trợ thương mại quốc tế | H69: TCHE417
A70: 25/6/2024 | D70: LUISS University | E70: Applied Statistics and Econometrics | F70: AC3 | G70: Thống kê và phân tích kinh doanh (Statistic and business analysis) | H70: TOA308E
A71: 25/6/2024 | D71: Hannam University | E71: Basic Vietnamese | F71: 23342 | G71: Tiếng Việt cơ bản 1 | H71: TVIH100/TVI100
A72: 25/6/2024 | D72: LUISS University | E72: Blockchain Technology and Fintech | F72: EFI06 | G72: Fintech (Financial Technology) | H72: TCH404E
A73: 25/6/2024 | D73: LUISS University | E73: Business Ethics | F73: GMP14 | G73: Tiêu chuẩn đạo đức hành nghề & quản trị doanh nghiệp (Professional Ethics and Coporate governance) | H73: DTU304E
A74: 25/6/2024 | D74: Trier Applied Science University | E74: Corporate Finance 2 | F74: 41998 | G74: Fundamentals of Finance | H74: TCH302E
A75: 25/6/2024 | D75: Trier Applied Science University | E75: Corporate Finance 2 | F75: 41998 | G75: Financial Analysis | H75: VJP305E
A76: 25/6/2024 | D76: LUISS University | E76: Digital Finance | F76: EM17 | G76: Fintech (Financial Technology) | H76: TCH404E
A77: 25/6/2024 | D77: Kanazawa University | E77: English Composition I | G77: Viết luận nâng cao (Advanced Writing) | H77: TAN213E
A78: 25/6/2024 | D78: Kanazawa University | E78: English Composition III | G78: Viết luận nâng cao (Advanced Writing) | H78: TAN213E
A79: 25/6/2024 | D79: Kanazawa University | E79: English Composition IV | G79: Viết luận nâng cao (Advanced Writing) | H79: TAN213E
A80: 25/6/2024 | D80: LUISS University | E80: Ethical Standards and Practices in Finance | F80: SMDEFCFA | G80: Tiêu chuẩn đạo đức hành nghề & quản trị doanh nghiệp | H80: DTUE304/DTU304E/DTU304
A81: 25/6/2024 | D81: LUISS University | E81: Finance statement analysis | F81: BAO9 | G81: Phân tích báo cáo tài chính (Financial Statement Analysis) | H81: TCH424E
A82: 25/6/2024 | D82: LUISS University | E82: Finance statement analysis | F82: M245 | G82: Phân tích báo cáo tài chính (Financial Statement Analysis) | H82: TCH424E
A83: 25/6/2024 | H83: KETE301
A84: 25/6/2024 | D84: National Research University, Higher School of Economics, St. Petersburg | E84: Financial Management | G84: Quản trị tài chính - lý thuyết và ứng dụng (Financial Management - Theory and Application) | H84: FIN370
A85: 25/6/2024 | D85: Minnesota State University, Mankato | E85: Human Resource Management | F85: MGMT340 | G85: Quản trị nguồn nhân lực | H85: QTRE403
A86: 25/6/2024 | D86: LUISS University | E86: International Accounting Standards | F86: EM32 | G86: Kế toán tài chính (Financial Accounting) | H86: KET301E
A87: 25/6/2024 | D87: Minnesota State University, Mankato | E87: International Economics | F87: ECON420 | G87: Kinh tế quốc tế | H87: KTEE308
A88: 25/6/2024 | D88: LUISS University | E88: International Human Resource Management | F88: M132 | G88: Quản trị nguồn nhân lực (Human Resource Management) | H88: QTR403E
A89: 25/6/2024 | D89: University of Victoria, Canada | E89: International Marketing | F89: IB416 | G89: Chiến lược Marketing quốc tế | H89: MKT403E
A90: 25/6/2024 | D90: LUISS University | E90: International Operations and Global Supply Chain | F90: DSM10 | G90: Quản lý chuỗi cung ứng và tính bền vững (Supply chain management and sustainability) | H90: TCH447E
A91: 25/6/2024 | D91: LUISS University | E91: International operations and Supply Chain | F91: M284 | G91: Quản lý chuỗi cung ứng và tính bền vững (Supply chain management and sustainability) | H91: TCH447E
A92: 25/6/2024 | D92: LUISS University | E92: International Project Finance & Sustainability | F92: MNG01 | G92: Quản trị dự án và quy trình nghiệp vụ (Business project and project management) | H92: TCH342E
A93: 25/6/2024 | D93: LUISS University | E93: International Project Finance & Sustainability | F93: MNG01 | G93: Tài trợ dự án (Project Financing) | H93: TCH426E
A94: 25/6/2024 | D94: Sciences Po University | E94: Introduction to Qualitative Methods | F94: BMET25A14 | G94: Phương pháp nghiên cứu trong kinh tế và kinh doanh | H94: KTE206
A95: 25/6/2024 | D95: Minnesota State University | E95: Investments | F95: FINA460 | G95: Quản trị danh mục đầu tư | H95: DTUE406
A96: 25/6/2024 | D96: Rikkyo University | E96: Marketing Research | F96: OW447 | G96: Phương pháp nghiên cứu trong kinh tế và kinh doanh (Research Methodology for Economics and Business) | H96: KTE206E
... A99: 25/6/2024 | D99: University of Victoria, Canada | E99: Personal Financial Management | F99: COM247 | G99: Quản trị tài chính cá nhân | H99: QTR441E
A100: 25/6/2024 | D100: FHNW | E100: Entrepreneurship and Innovation | G100: Entrepreneurship and Innovation | H100: TCHE446 | I100: Ko phải của Viện KT&KDQT, chờ gửi lại
A101: 25/6/2024
A102: 25/6/2024 | D102: LUISS University | E102: Quantitative Methods for Finance | F102: M248 | G102: Phương pháp lượng cho tài chính (Quantitative methods for finance) | H102: TCH442E
...
